{
  "token": " 5 ",
  "instances": [
    {
      "index": 29,
      "pos": "Bae_TB_1_15813",
      "token_next_uri": "5 g.json",
      "token_prev_uri": ", 5.json",
      "chN": 120
    },
    {
      "index": 230,
      "pos": "Bae_TB_2_5901",
      "token_next_uri": "5 o.json",
      "token_prev_uri": "r 5.json",
      "chN": 255
    },
    {
      "index": 164,
      "pos": "Bae_TB_2_14081",
      "token_next_uri": "5 U.json",
      "token_prev_uri": "m 5.json",
      "chN": 175
    },
    {
      "index": 57,
      "pos": "Bae_TB_2_16459",
      "token_next_uri": "5 K.json",
      "token_prev_uri": "a 5.json",
      "chN": 112
    },
    {
      "index": 29,
      "pos": "Bae_TB_2_16476",
      "token_next_uri": "5 U.json",
      "token_prev_uri": "r 5.json",
      "chN": 68
    },
    {
      "index": 6,
      "pos": "Bae_TB_3_8729",
      "token_next_uri": "5 Z.json",
      "token_prev_uri": "f 5.json",
      "chN": 251
    }
  ]
}