{
  "token": "4U+002E ",
  "instances": [
    {
      "index": 0,
      "pos": "Bae_MF_1_738",
      "token_next_uri": "U+002E F.json",
      "token_prev_uri": " 4U+002E.json",
      "chN": 10
    },
    {
      "index": 0,
      "pos": "Bae_MF_1_2840",
      "token_next_uri": "U+002E A.json",
      "token_prev_uri": " 4U+002E.json",
      "chN": 8
    },
    {
      "index": 0,
      "pos": "Bae_MF_2_258",
      "token_next_uri": "U+002E M.json",
      "token_prev_uri": " 4U+002E.json",
      "chN": 7
    },
    {
      "index": 0,
      "pos": "Bae_MF_2_5581",
      "token_next_uri": "U+002E J.json",
      "token_prev_uri": " 4U+002E.json",
      "chN": 7
    },
    {
      "index": 1,
      "pos": "Bae_MF_2_5712",
      "token_next_uri": "U+002E J.json",
      "token_prev_uri": "24U+002E.json",
      "chN": 8
    },
    {
      "index": 1,
      "pos": "Bae_MF_2_5781",
      "token_next_uri": "U+002E J.json",
      "token_prev_uri": "24U+002E.json",
      "chN": 8
    },
    {
      "index": 1,
      "pos": "Bae_MF_2_6802",
      "token_next_uri": "U+002E J.json",
      "token_prev_uri": "24U+002E.json",
      "chN": 8
    },
    {
      "index": 1,
      "pos": "Bae_MF_2_6836",
      "token_next_uri": "U+002E J.json",
      "token_prev_uri": "24U+002E.json",
      "chN": 8
    },
    {
      "index": 0,
      "pos_pr": "Bae_MF_2_8700",
      "pos_nxt": "Bae_MF_2_8702",
      "token_next_uri": "U+002E u.json",
      "token_prev_uri": "14U+002E.json",
      "chN": 4
    },
    {
      "index": 1,
      "pos": "Bae_MF_2_8918",
      "token_next_uri": "U+002E J.json",
      "token_prev_uri": "24U+002E.json",
      "chN": 8
    },
    {
      "index": 0,
      "pos": "Bae_MF_2_10964",
      "token_next_uri": "U+002E D.json",
      "token_prev_uri": " 4U+002E.json",
      "chN": 7
    },
    {
      "index": 1,
      "pos": "Bae_MF_2_10978",
      "token_next_uri": "U+002E J.json",
      "token_prev_uri": "24U+002E.json",
      "chN": 8
    },
    {
      "index": 1,
      "pos": "Bae_MF_2_12219",
      "token_next_uri": "U+002E A.json",
      "token_prev_uri": "24U+002E.json",
      "chN": 10
    },
    {
      "index": 169,
      "pos": "Bae_MF_6-1_398",
      "token_next_uri": "U+002E I.json",
      "token_prev_uri": "04U+002E.json",
      "chN": 190
    },
    {
      "index": 0,
      "pos": "Bae_MF_6-2_1658",
      "token_next_uri": "U+002E G.json",
      "token_prev_uri": " 4U+002E.json",
      "chN": 3
    }
  ]
}