{
  "token": "ges",
  "instances": [
    {
      "index": 32,
      "pos": "Bae_MF_6-2_207",
      "token_next_uri": "ese.json",
      "token_prev_uri": "rge.json",
      "chN": 125
    },
    {
      "index": 9,
      "pos": "Bae_MF_6-2_213",
      "token_next_uri": "ese.json",
      "token_prev_uri": "bge.json",
      "chN": 84
    },
    {
      "index": 40,
      "pos": "Bae_MF_6-2_345",
      "token_next_uri": "esu.json",
      "token_prev_uri": " ge.json",
      "chN": 155
    },
    {
      "index": 3,
      "pos": "Bae_MF_6-2_352",
      "token_next_uri": "esc.json",
      "token_prev_uri": "nge.json",
      "chN": 14
    },
    {
      "index": 44,
      "pos": "Bae_MF_6-2_377",
      "token_next_uri": "esu.json",
      "token_prev_uri": " ge.json",
      "chN": 297
    },
    {
      "index": 124,
      "pos": "Bae_MF_6-2_377",
      "token_next_uri": "esi.json",
      "token_prev_uri": " ge.json",
      "chN": 297
    },
    {
      "index": 257,
      "pos": "Bae_MF_6-2_377",
      "token_next_uri": "ese.json",
      "token_prev_uri": "rge.json",
      "chN": 297
    },
    {
      "index": 48,
      "pos": "Bae_MF_6-2_381",
      "token_next_uri": "esc.json",
      "token_prev_uri": " ge.json",
      "chN": 79
    },
    {
      "index": 73,
      "pos": "Bae_MF_6-2_454",
      "token_next_uri": "est.json",
      "token_prev_uri": "rge.json",
      "chN": 101
    },
    {
      "index": 0,
      "pos": "Bae_MF_6-2_766",
      "token_next_uri": "ese.json",
      "token_prev_uri": " ge.json",
      "chN": 72
    },
    {
      "index": 77,
      "pos": "Bae_MF_6-2_786",
      "token_next_uri": "esc.json",
      "token_prev_uri": "rge.json",
      "chN": 139
    },
    {
      "index": 4,
      "pos": "Bae_MF_6-2_809",
      "token_next_uri": "esc.json",
      "token_prev_uri": "ßge.json",
      "chN": 170
    },
    {
      "index": 4,
      "pos": "Bae_MF_6-2_890",
      "token_next_uri": "esc.json",
      "token_prev_uri": "sge.json",
      "chN": 55
    },
    {
      "index": 10,
      "pos": "Bae_MF_6-2_918",
      "token_next_uri": "esc.json",
      "token_prev_uri": "rge.json",
      "chN": 61
    },
    {
      "index": 5,
      "pos": "Bae_MF_6-2_1004",
      "token_next_uri": "esc.json",
      "token_prev_uri": " ge.json",
      "chN": 160
    },
    {
      "index": 35,
      "pos": "Bae_MF_6-2_1004",
      "token_next_uri": "esi.json",
      "token_prev_uri": "nge.json",
      "chN": 160
    },
    {
      "index": 1,
      "pos": "Bae_MF_6-2_1101",
      "token_next_uri": "est.json",
      "token_prev_uri": " ge.json",
      "chN": 150
    },
    {
      "index": 19,
      "pos": "Bae_MF_6-2_1275",
      "token_next_uri": "ese.json",
      "token_prev_uri": "sge.json",
      "chN": 99
    },
    {
      "index": 99,
      "pos": "Bae_MF_6-2_1307",
      "token_next_uri": "ese.json",
      "token_prev_uri": "nge.json",
      "chN": 118
    },
    {
      "index": 70,
      "pos": "Bae_MF_6-2_1502",
      "token_next_uri": "ese.json",
      "token_prev_uri": " ge.json",
      "chN": 141
    },
    {
      "index": 4,
      "pos": "Bae_MF_6-2_1587",
      "token_next_uri": "esp.json",
      "token_prev_uri": "sge.json",
      "chN": 41
    },
    {
      "index": 153,
      "pos": "Bae_MF_6-2_1680",
      "token_next_uri": "esa.json",
      "token_prev_uri": " ge.json",
      "chN": 186
    },
    {
      "index": 3,
      "pos": "Bae_MF_6-2_1781",
      "token_next_uri": "est.json",
      "token_prev_uri": "uge.json",
      "chN": 62
    },
    {
      "index": 169,
      "pos": "Bae_MF_6-2_1879",
      "token_next_uri": "esc.json",
      "token_prev_uri": "sge.json",
      "chN": 588
    },
    {
      "index": 8,
      "pos": "Bae_MF_6-2_1996",
      "token_next_uri": "ess.json",
      "token_prev_uri": "rge.json",
      "chN": 242
    },
    {
      "index": 177,
      "pos": "Bae_MF_6-2_2268",
      "token_next_uri": "esc.json",
      "token_prev_uri": " ge.json",
      "chN": 291
    },
    {
      "index": 1,
      "pos": "Bae_MF_6-2_2460",
      "token_next_uri": "ese.json",
      "token_prev_uri": " ge.json",
      "chN": 40
    },
    {
      "index": 46,
      "pos": "Bae_MF_6-2_2469",
      "token_next_uri": "esc.json",
      "token_prev_uri": " ge.json",
      "chN": 80
    },
    {
      "index": 8,
      "pos": "Bae_MF_6-2_2556",
      "token_next_uri": "esi.json",
      "token_prev_uri": "nge.json",
      "chN": 185
    },
    {
      "index": 45,
      "pos": "Bae_MF_6-2_2556",
      "token_next_uri": "es .json",
      "token_prev_uri": "nge.json",
      "chN": 185
    },
    {
      "index": 117,
      "pos": "Bae_MF_6-2_2786",
      "token_next_uri": "esc.json",
      "token_prev_uri": "sge.json",
      "chN": 130
    },
    {
      "index": 21,
      "pos": "Bae_MF_6-2_2919",
      "token_next_uri": "esi.json",
      "token_prev_uri": " ge.json",
      "chN": 158
    },
    {
      "index": 41,
      "pos": "Bae_MF_6-2_2931",
      "token_next_uri": "esc.json",
      "token_prev_uri": "rge.json",
      "chN": 167
    },
    {
      "index": 17,
      "pos": "Bae_MF_6-2_3499",
      "token_next_uri": "es .json",
      "token_prev_uri": "age.json",
      "chN": 45
    },
    {
      "index": 17,
      "pos": "Bae_MF_6-2_3637",
      "token_next_uri": "esp.json",
      "token_prev_uri": "sge.json",
      "chN": 74
    },
    {
      "index": 150,
      "pos": "Bae_MF_6-2_3723",
      "token_next_uri": "esc.json",
      "token_prev_uri": "sge.json",
      "chN": 236
    },
    {
      "index": 5,
      "pos": "Bae_MF_6-2_3764",
      "token_next_uri": "esi.json",
      "token_prev_uri": " ge.json",
      "chN": 138
    },
    {
      "index": 0,
      "pos": "Bae_MF_6-2_3843",
      "token_next_uri": "esa.json",
      "token_prev_uri": "5ge.json",
      "chN": 18
    },
    {
      "index": 35,
      "pos": "Bae_MF_6-2_4075",
      "token_next_uri": "esc.json",
      "token_prev_uri": " ge.json",
      "chN": 85
    },
    {
      "index": 24,
      "pos": "Bae_MF_6-2_4091",
      "token_next_uri": "esc.json",
      "token_prev_uri": " ge.json",
      "chN": 61
    },
    {
      "index": 1,
      "pos": "Bae_MF_6-2_4490",
      "token_next_uri": "esa.json",
      "token_prev_uri": " ge.json",
      "chN": 69
    },
    {
      "index": 107,
      "pos": "Bae_MF_6-2_4528",
      "token_next_uri": "est.json",
      "token_prev_uri": "nge.json",
      "chN": 154
    },
    {
      "index": 1,
      "pos": "Bae_MF_6-2_4561",
      "token_next_uri": "esc.json",
      "token_prev_uri": " ge.json",
      "chN": 26
    },
    {
      "index": 19,
      "pos": "Bae_MF_6-2_4612",
      "token_next_uri": "esU+002E.json",
      "token_prev_uri": "age.json",
      "chN": 169
    },
    {
      "index": 20,
      "pos": "Bae_MF_6-2_4650",
      "token_next_uri": "esp.json",
      "token_prev_uri": " ge.json",
      "chN": 41
    },
    {
      "index": 37,
      "pos": "Bae_MF_6-2_4663",
      "token_next_uri": "esc.json",
      "token_prev_uri": "sge.json",
      "chN": 64
    },
    {
      "index": 154,
      "pos": "Bae_MF_6-2_4816",
      "token_next_uri": "esc.json",
      "token_prev_uri": "tge.json",
      "chN": 203
    },
    {
      "index": 81,
      "pos": "Bae_MF_6-2_4943",
      "token_next_uri": "ese.json",
      "token_prev_uri": "nge.json",
      "chN": 127
    },
    {
      "index": 10,
      "pos": "Bae_MF_6-2_5455",
      "token_next_uri": "est.json",
      "token_prev_uri": " ge.json",
      "chN": 85
    },
    {
      "index": 237,
      "pos": "Bae_MF_6-2_5459",
      "token_next_uri": "esc.json",
      "token_prev_uri": " ge.json",
      "chN": 656
    },
    {
      "index": 187,
      "pos": "Bae_MF_6-2_5571",
      "token_next_uri": "esp.json",
      "token_prev_uri": "sge.json",
      "chN": 231
    },
    {
      "index": 17,
      "pos": "Bae_MF_6-2_5590",
      "token_next_uri": "es .json",
      "token_prev_uri": "ige.json",
      "chN": 110
    },
    {
      "index": 108,
      "pos": "Bae_MF_6-2_5617",
      "token_next_uri": "esg.json",
      "token_prev_uri": "ege.json",
      "chN": 217
    },
    {
      "index": 15,
      "pos": "Bae_MF_6-2_5743",
      "token_next_uri": "ese.json",
      "token_prev_uri": " ge.json",
      "chN": 195
    },
    {
      "index": 99,
      "pos": "Bae_MF_6-2_5757",
      "token_next_uri": "esp.json",
      "token_prev_uri": " ge.json",
      "chN": 245
    },
    {
      "index": 490,
      "pos": "Bae_MF_6-2_5970",
      "token_next_uri": "esc.json",
      "token_prev_uri": " ge.json",
      "chN": 585
    },
    {
      "index": 375,
      "pos": "Bae_MF_6-2_5979",
      "token_next_uri": "esc.json",
      "token_prev_uri": "dge.json",
      "chN": 491
    },
    {
      "index": 429,
      "pos": "Bae_MF_6-2_5979",
      "token_next_uri": "es .json",
      "token_prev_uri": "nge.json",
      "chN": 491
    },
    {
      "index": 40,
      "pos": "Bae_MF_6-2_5989",
      "token_next_uri": "es .json",
      "token_prev_uri": "nge.json",
      "chN": 184
    },
    {
      "index": 80,
      "pos": "Bae_MF_6-2_5989",
      "token_next_uri": "esc.json",
      "token_prev_uri": "sge.json",
      "chN": 184
    },
    {
      "index": 67,
      "pos": "Bae_MF_6-2_6026",
      "token_next_uri": "esp.json",
      "token_prev_uri": "sge.json",
      "chN": 130
    },
    {
      "index": 226,
      "pos": "Bae_MF_6-2_6147",
      "token_next_uri": "esc.json",
      "token_prev_uri": "bge.json",
      "chN": 305
    },
    {
      "index": 231,
      "pos": "Bae_MF_6-2_6237",
      "token_next_uri": "est.json",
      "token_prev_uri": " ge.json",
      "chN": 687
    },
    {
      "index": 253,
      "pos": "Bae_MF_6-2_6247",
      "token_next_uri": "esc.json",
      "token_prev_uri": " ge.json",
      "chN": 575
    },
    {
      "index": 118,
      "pos": "Bae_MF_6-2_6260",
      "token_next_uri": "es .json",
      "token_prev_uri": "ige.json",
      "chN": 291
    },
    {
      "index": 151,
      "pos": "Bae_MF_6-2_6294",
      "token_next_uri": "esc.json",
      "token_prev_uri": "nge.json",
      "chN": 320
    },
    {
      "index": 167,
      "pos": "Bae_MF_6-2_6294",
      "token_next_uri": "esp.json",
      "token_prev_uri": "ege.json",
      "chN": 320
    },
    {
      "index": 4,
      "pos": "Bae_MF_6-2_6313",
      "token_next_uri": "esp.json",
      "token_prev_uri": "sge.json",
      "chN": 548
    },
    {
      "index": 439,
      "pos": "Bae_MF_6-2_6313",
      "token_next_uri": "esi.json",
      "token_prev_uri": " ge.json",
      "chN": 548
    },
    {
      "index": 339,
      "pos": "Bae_MF_6-2_6341",
      "token_next_uri": "esc.json",
      "token_prev_uri": " ge.json",
      "chN": 620
    },
    {
      "index": 245,
      "pos": "Bae_MF_6-2_6344",
      "token_next_uri": "est.json",
      "token_prev_uri": " ge.json",
      "chN": 562
    },
    {
      "index": 498,
      "pos": "Bae_MF_6-2_6344",
      "token_next_uri": "esc.json",
      "token_prev_uri": " ge.json",
      "chN": 562
    },
    {
      "index": 38,
      "pos": "Bae_TB_1_150",
      "token_next_uri": "es,.json",
      "token_prev_uri": "ige.json",
      "chN": 55
    },
    {
      "index": 51,
      "pos": "Bae_TB_1_150",
      "token_next_uri": "es .json",
      "token_prev_uri": "uge.json",
      "chN": 55
    },
    {
      "index": 20,
      "pos": "Bae_TB_1_448",
      "token_next_uri": "ese.json",
      "token_prev_uri": "nge.json",
      "chN": 117
    },
    {
      "index": 1,
      "pos": "Bae_TB_1_554",
      "token_next_uri": "esp.json",
      "token_prev_uri": " ge.json",
      "chN": 29
    },
    {
      "index": 29,
      "pos": "Bae_TB_1_700",
      "token_next_uri": "est.json",
      "token_prev_uri": "rge.json",
      "chN": 69
    },
    {
      "index": 4,
      "pos": "Bae_TB_1_704",
      "token_next_uri": "ese.json",
      "token_prev_uri": "rge.json",
      "chN": 397
    },
    {
      "index": 98,
      "pos": "Bae_TB_1_704",
      "token_next_uri": "est.json",
      "token_prev_uri": "nge.json",
      "chN": 397
    },
    {
      "index": 306,
      "pos": "Bae_TB_1_704",
      "token_next_uri": "esc.json",
      "token_prev_uri": " ge.json",
      "chN": 397
    },
    {
      "index": 6,
      "pos": "Bae_TB_1_710",
      "token_next_uri": "es .json",
      "token_prev_uri": "age.json",
      "chN": 9
    },
    {
      "index": 36,
      "pos": "Bae_TB_1_716",
      "token_next_uri": "eso.json",
      "token_prev_uri": " ge.json",
      "chN": 60
    },
    {
      "index": 6,
      "pos": "Bae_TB_1_731",
      "token_next_uri": "es .json",
      "token_prev_uri": "age.json",
      "chN": 9
    },
    {
      "index": 6,
      "pos": "Bae_TB_1_743",
      "token_next_uri": "es .json",
      "token_prev_uri": "age.json",
      "chN": 9
    },
    {
      "index": 57,
      "pos": "Bae_TB_1_745",
      "token_next_uri": "esc.json",
      "token_prev_uri": " ge.json",
      "chN": 77
    },
    {
      "index": 99,
      "pos": "Bae_TB_1_778",
      "token_next_uri": "esa.json",
      "token_prev_uri": " ge.json",
      "chN": 205
    },
    {
      "index": 32,
      "pos": "Bae_TB_1_864",
      "token_next_uri": "ese.json",
      "token_prev_uri": "nge.json",
      "chN": 48
    },
    {
      "index": 6,
      "pos": "Bae_TB_1_963",
      "token_next_uri": "es .json",
      "token_prev_uri": "age.json",
      "chN": 9
    },
    {
      "index": 39,
      "pos": "Bae_TB_1_973",
      "token_next_uri": "ese.json",
      "token_prev_uri": "nge.json",
      "chN": 48
    },
    {
      "index": 38,
      "pos": "Bae_TB_1_1161",
      "token_next_uri": "ese.json",
      "token_prev_uri": "nge.json",
      "chN": 115
    },
    {
      "index": 101,
      "pos": "Bae_TB_1_1333",
      "token_next_uri": "ese.json",
      "token_prev_uri": "nge.json",
      "chN": 108
    },
    {
      "index": 351,
      "pos": "Bae_TB_1_1418",
      "token_next_uri": "es .json",
      "token_prev_uri": "age.json",
      "chN": 1315
    },
    {
      "index": 6,
      "pos": "Bae_TB_1_1420",
      "token_next_uri": "es .json",
      "token_prev_uri": "age.json",
      "chN": 9
    },
    {
      "index": 187,
      "pos": "Bae_TB_1_1426",
      "token_next_uri": "ese.json",
      "token_prev_uri": " ge.json",
      "chN": 1027
    },
    {
      "index": 895,
      "pos": "Bae_TB_1_1426",
      "token_next_uri": "esc.json",
      "token_prev_uri": " ge.json",
      "chN": 1027
    },
    {
      "index": 29,
      "pos": "Bae_TB_1_1432",
      "token_next_uri": "esp.json",
      "token_prev_uri": " ge.json",
      "chN": 276
    },
    {
      "index": 403,
      "pos": "Bae_TB_1_1438",
      "token_next_uri": "est.json",
      "token_prev_uri": " ge.json",
      "chN": 529
    },
    {
      "index": 478,
      "pos": "Bae_TB_1_1438",
      "token_next_uri": "es .json",
      "token_prev_uri": "age.json",
      "chN": 529
    },
    {
      "index": 6,
      "pos": "Bae_TB_1_1446",
      "token_next_uri": "es .json",
      "token_prev_uri": "age.json",
      "chN": 9
    },
    {
      "index": 241,
      "pos": "Bae_TB_1_1451",
      "token_next_uri": "est.json",
      "token_prev_uri": "hge.json",
      "chN": 265
    },
    {
      "index": 27,
      "pos": "Bae_TB_1_1658",
      "token_next_uri": "esc.json",
      "token_prev_uri": "ige.json",
      "chN": 41
    },
    {
      "index": 182,
      "pos": "Bae_TB_1_1671",
      "token_next_uri": "esc.json",
      "token_prev_uri": "dge.json",
      "chN": 228
    },
    {
      "index": 88,
      "pos": "Bae_TB_1_1712",
      "token_next_uri": "es .json",
      "token_prev_uri": "ige.json",
      "chN": 258
    },
    {
      "index": 184,
      "pos": "Bae_TB_1_1712",
      "token_next_uri": "est.json",
      "token_prev_uri": " ge.json",
      "chN": 258
    },
    {
      "index": 36,
      "pos": "Bae_TB_1_1726",
      "token_next_uri": "esä.json",
      "token_prev_uri": " ge.json",
      "chN": 49
    },
    {
      "index": 48,
      "pos": "Bae_TB_1_1750",
      "token_next_uri": "ese.json",
      "token_prev_uri": "nge.json",
      "chN": 115
    },
    {
      "index": 46,
      "pos": "Bae_TB_1_1974",
      "token_next_uri": "ese.json",
      "token_prev_uri": "nge.json",
      "chN": 191
    },
    {
      "index": 9,
      "pos": "Bae_TB_1_2039",
      "token_next_uri": "esa.json",
      "token_prev_uri": "bge.json",
      "chN": 184
    },
    {
      "index": 28,
      "pos": "Bae_TB_1_2107",
      "token_next_uri": "esc.json",
      "token_prev_uri": " ge.json",
      "chN": 59
    },
    {
      "index": 107,
      "pos": "Bae_TB_1_2188",
      "token_next_uri": "esi.json",
      "token_prev_uri": "nge.json",
      "chN": 174
    },
    {
      "index": 96,
      "pos": "Bae_TB_1_2206",
      "token_next_uri": "ese.json",
      "token_prev_uri": " ge.json",
      "chN": 215
    },
    {
      "index": 158,
      "pos": "Bae_TB_1_2206",
      "token_next_uri": "eso.json",
      "token_prev_uri": "bge.json",
      "chN": 215
    },
    {
      "index": 32,
      "pos": "Bae_TB_1_2209",
      "token_next_uri": "est.json",
      "token_prev_uri": " ge.json",
      "chN": 88
    },
    {
      "index": 4,
      "pos": "Bae_TB_1_2230",
      "token_next_uri": "esc.json",
      "token_prev_uri": "rge.json",
      "chN": 16
    },
    {
      "index": 88,
      "pos": "Bae_TB_1_2402",
      "token_next_uri": "esp.json",
      "token_prev_uri": "nge.json",
      "chN": 109
    },
    {
      "index": 38,
      "pos": "Bae_TB_1_2670",
      "token_next_uri": "es .json",
      "token_prev_uri": "ige.json",
      "chN": 101
    },
    {
      "index": 65,
      "pos": "Bae_TB_1_2776",
      "token_next_uri": "est.json",
      "token_prev_uri": " ge.json",
      "chN": 158
    },
    {
      "index": 9,
      "pos": "Bae_TB_1_2929",
      "token_next_uri": "est.json",
      "token_prev_uri": " ge.json",
      "chN": 226
    },
    {
      "index": 332,
      "pos": "Bae_TB_1_2953",
      "token_next_uri": "est.json",
      "token_prev_uri": " ge.json",
      "chN": 378
    },
    {
      "index": 48,
      "pos": "Bae_TB_1_3000",
      "token_next_uri": "est.json",
      "token_prev_uri": " ge.json",
      "chN": 145
    },
    {
      "index": 138,
      "pos": "Bae_TB_1_3009",
      "token_next_uri": "esc.json",
      "token_prev_uri": "zge.json",
      "chN": 333
    },
    {
      "index": 90,
      "pos": "Bae_TB_1_3039",
      "token_next_uri": "ese.json",
      "token_prev_uri": "sge.json",
      "chN": 259
    },
    {
      "index": 27,
      "pos": "Bae_TB_1_3073",
      "token_next_uri": "est.json",
      "token_prev_uri": " ge.json",
      "chN": 242
    },
    {
      "index": 75,
      "pos": "Bae_TB_1_3073",
      "token_next_uri": "est.json",
      "token_prev_uri": " ge.json",
      "chN": 242
    },
    {
      "index": 81,
      "pos": "Bae_TB_1_3073",
      "token_next_uri": "es .json",
      "token_prev_uri": "ige.json",
      "chN": 242
    },
    {
      "index": 1,
      "pos": "Bae_TB_1_3081",
      "token_next_uri": "esp.json",
      "token_prev_uri": " ge.json",
      "chN": 84
    },
    {
      "index": 140,
      "pos": "Bae_TB_1_3112",
      "token_next_uri": "esp.json",
      "token_prev_uri": " ge.json",
      "chN": 307
    },
    {
      "index": 117,
      "pos": "Bae_TB_1_3118",
      "token_next_uri": "ese.json",
      "token_prev_uri": " ge.json",
      "chN": 199
    },
    {
      "index": 173,
      "pos": "Bae_TB_1_3131",
      "token_next_uri": "esc.json",
      "token_prev_uri": " ge.json",
      "chN": 185
    },
    {
      "index": 33,
      "pos": "Bae_TB_1_3451",
      "token_next_uri": "esc.json",
      "token_prev_uri": " ge.json",
      "chN": 52
    },
    {
      "index": 24,
      "pos": "Bae_TB_1_3496",
      "token_next_uri": "es .json",
      "token_prev_uri": "ige.json",
      "chN": 62
    },
    {
      "index": 97,
      "pos": "Bae_TB_1_3608",
      "token_next_uri": "esp.json",
      "token_prev_uri": "sge.json",
      "chN": 180
    },
    {
      "index": 136,
      "pos": "Bae_TB_1_3623",
      "token_next_uri": "ese.json",
      "token_prev_uri": "tge.json",
      "chN": 185
    },
    {
      "index": 11,
      "pos": "Bae_TB_1_3664",
      "token_next_uri": "ese.json",
      "token_prev_uri": "nge.json",
      "chN": 266
    },
    {
      "index": 37,
      "pos": "Bae_TB_1_3678",
      "token_next_uri": "esa.json",
      "token_prev_uri": " ge.json",
      "chN": 63
    },
    {
      "index": 3,
      "pos": "Bae_TB_1_3682",
      "token_next_uri": "est.json",
      "token_prev_uri": "uge.json",
      "chN": 187
    },
    {
      "index": 75,
      "pos": "Bae_TB_1_3698",
      "token_next_uri": "esu.json",
      "token_prev_uri": " ge.json",
      "chN": 176
    },
    {
      "index": 146,
      "pos": "Bae_TB_1_3698",
      "token_next_uri": "est.json",
      "token_prev_uri": "sge.json",
      "chN": 176
    },
    {
      "index": 17,
      "pos": "Bae_TB_1_3723",
      "token_next_uri": "est.json",
      "token_prev_uri": "hge.json",
      "chN": 86
    },
    {
      "index": 29,
      "pos": "Bae_TB_1_3764",
      "token_next_uri": "est.json",
      "token_prev_uri": "nge.json",
      "chN": 407
    },
    {
      "index": 256,
      "pos": "Bae_TB_1_3766",
      "token_next_uri": "ese.json",
      "token_prev_uri": "nge.json",
      "chN": 265
    },
    {
      "index": 120,
      "pos": "Bae_TB_1_3769",
      "token_next_uri": "est.json",
      "token_prev_uri": " ge.json",
      "chN": 443
    },
    {
      "index": 293,
      "pos": "Bae_TB_1_3769",
      "token_next_uri": "esc.json",
      "token_prev_uri": " ge.json",
      "chN": 443
    },
    {
      "index": 341,
      "pos": "Bae_TB_1_3816",
      "token_next_uri": "esc.json",
      "token_prev_uri": "sge.json",
      "chN": 429
    },
    {
      "index": 406,
      "pos": "Bae_TB_1_3816",
      "token_next_uri": "ese.json",
      "token_prev_uri": "nge.json",
      "chN": 429
    },
    {
      "index": 418,
      "pos": "Bae_TB_1_3816",
      "token_next_uri": "esi.json",
      "token_prev_uri": " ge.json",
      "chN": 429
    },
    {
      "index": 6,
      "pos": "Bae_TB_1_3922",
      "token_next_uri": "esc.json",
      "token_prev_uri": "sge.json",
      "chN": 79
    },
    {
      "index": 69,
      "pos": "Bae_TB_1_3948",
      "token_next_uri": "est.json",
      "token_prev_uri": "nge.json",
      "chN": 166
    },
    {
      "index": 29,
      "pos": "Bae_TB_1_3957",
      "token_next_uri": "esc.json",
      "token_prev_uri": "rge.json",
      "chN": 133
    },
    {
      "index": 104,
      "pos": "Bae_TB_1_4059",
      "token_next_uri": "esc.json",
      "token_prev_uri": "nge.json",
      "chN": 114
    },
    {
      "index": 171,
      "pos": "Bae_TB_1_4188",
      "token_next_uri": "ese.json",
      "token_prev_uri": " ge.json",
      "chN": 179
    },
    {
      "index": 43,
      "pos": "Bae_TB_1_4451",
      "token_next_uri": "est.json",
      "token_prev_uri": " ge.json",
      "chN": 69
    },
    {
      "index": 182,
      "pos": "Bae_TB_1_4569",
      "token_next_uri": "esc.json",
      "token_prev_uri": "nge.json",
      "chN": 367
    },
    {
      "index": 30,
      "pos": "Bae_TB_1_4620",
      "token_next_uri": "es .json",
      "token_prev_uri": "ige.json",
      "chN": 181
    },
    {
      "index": 24,
      "pos": "Bae_TB_1_4718",
      "token_next_uri": "ese.json",
      "token_prev_uri": "sge.json",
      "chN": 165
    },
    {
      "index": 144,
      "pos": "Bae_TB_1_4755",
      "token_next_uri": "ese.json",
      "token_prev_uri": "sge.json",
      "chN": 341
    },
    {
      "index": 1,
      "pos": "Bae_TB_1_4787",
      "token_next_uri": "esc.json",
      "token_prev_uri": " ge.json",
      "chN": 109
    },
    {
      "index": 91,
      "pos": "Bae_TB_1_4865",
      "token_next_uri": "esc.json",
      "token_prev_uri": " ge.json",
      "chN": 115
    },
    {
      "index": 21,
      "pos": "Bae_TB_1_4923",
      "token_next_uri": "es,.json",
      "token_prev_uri": "ige.json",
      "chN": 55
    },
    {
      "index": 35,
      "pos": "Bae_TB_1_4923",
      "token_next_uri": "es .json",
      "token_prev_uri": "ige.json",
      "chN": 55
    },
    {
      "index": 9,
      "pos": "Bae_TB_1_5021",
      "token_next_uri": "esu.json",
      "token_prev_uri": " ge.json",
      "chN": 71
    },
    {
      "index": 88,
      "pos": "Bae_TB_1_5149",
      "token_next_uri": "es .json",
      "token_prev_uri": "ige.json",
      "chN": 158
    },
    {
      "index": 14,
      "pos": "Bae_TB_1_5502",
      "token_next_uri": "ese.json",
      "token_prev_uri": " ge.json",
      "chN": 185
    },
    {
      "index": 376,
      "pos": "Bae_TB_1_5756",
      "token_next_uri": "ese.json",
      "token_prev_uri": " ge.json",
      "chN": 598
    },
    {
      "index": 20,
      "pos": "Bae_TB_1_5780",
      "token_next_uri": "est.json",
      "token_prev_uri": " ge.json",
      "chN": 704
    },
    {
      "index": 525,
      "pos": "Bae_TB_1_5780",
      "token_next_uri": "esp.json",
      "token_prev_uri": "sge.json",
      "chN": 704
    },
    {
      "index": 543,
      "pos": "Bae_TB_1_5780",
      "token_next_uri": "esi.json",
      "token_prev_uri": "nge.json",
      "chN": 704
    },
    {
      "index": 78,
      "pos": "Bae_TB_1_5818",
      "token_next_uri": "esp.json",
      "token_prev_uri": "sge.json",
      "chN": 155
    },
    {
      "index": 58,
      "pos": "Bae_TB_1_5858",
      "token_next_uri": "esc.json",
      "token_prev_uri": " ge.json",
      "chN": 84
    },
    {
      "index": 13,
      "pos": "Bae_TB_1_5912",
      "token_next_uri": "ese.json",
      "token_prev_uri": "bge.json",
      "chN": 29
    },
    {
      "index": 5,
      "pos": "Bae_TB_1_5937",
      "token_next_uri": "esp.json",
      "token_prev_uri": " ge.json",
      "chN": 98
    },
    {
      "index": 69,
      "pos": "Bae_TB_1_5949",
      "token_next_uri": "esu.json",
      "token_prev_uri": "sge.json",
      "chN": 139
    },
    {
      "index": 57,
      "pos": "Bae_TB_1_5993",
      "token_next_uri": "es .json",
      "token_prev_uri": "age.json",
      "chN": 65
    },
    {
      "index": 96,
      "pos": "Bae_TB_1_6054",
      "token_next_uri": "esp.json",
      "token_prev_uri": " ge.json",
      "chN": 118
    },
    {
      "index": 150,
      "pos": "Bae_TB_1_6147",
      "token_next_uri": "ese.json",
      "token_prev_uri": "bge.json",
      "chN": 335
    },
    {
      "index": 54,
      "pos": "Bae_TB_1_6195",
      "token_next_uri": "esc.json",
      "token_prev_uri": "sge.json",
      "chN": 176
    },
    {
      "index": 44,
      "pos": "Bae_TB_1_6199",
      "token_next_uri": "esc.json",
      "token_prev_uri": "nge.json",
      "chN": 83
    },
    {
      "index": 105,
      "pos": "Bae_TB_1_6206",
      "token_next_uri": "es .json",
      "token_prev_uri": "ige.json",
      "chN": 229
    },
    {
      "index": 141,
      "pos": "Bae_TB_1_6206",
      "token_next_uri": "esc.json",
      "token_prev_uri": "sge.json",
      "chN": 229
    },
    {
      "index": 222,
      "pos": "Bae_TB_1_6210",
      "token_next_uri": "ese.json",
      "token_prev_uri": "sge.json",
      "chN": 267
    },
    {
      "index": 24,
      "pos": "Bae_TB_1_6241",
      "token_next_uri": "est.json",
      "token_prev_uri": " ge.json",
      "chN": 35
    },
    {
      "index": 40,
      "pos": "Bae_TB_1_6320",
      "token_next_uri": "esc.json",
      "token_prev_uri": "sge.json",
      "chN": 86
    },
    {
      "index": 154,
      "pos": "Bae_TB_1_6501",
      "token_next_uri": "ess.json",
      "token_prev_uri": "rge.json",
      "chN": 161
    },
    {
      "index": 107,
      "pos": "Bae_TB_1_6591",
      "token_next_uri": "esc.json",
      "token_prev_uri": "rge.json",
      "chN": 145
    },
    {
      "index": 12,
      "pos": "Bae_TB_1_6659",
      "token_next_uri": "es .json",
      "token_prev_uri": "nge.json",
      "chN": 15
    },
    {
      "index": 137,
      "pos": "Bae_TB_1_6724",
      "token_next_uri": "esc.json",
      "token_prev_uri": " ge.json",
      "chN": 178
    },
    {
      "index": 18,
      "pos": "Bae_TB_1_6727",
      "token_next_uri": "esc.json",
      "token_prev_uri": " ge.json",
      "chN": 76
    },
    {
      "index": 32,
      "pos": "Bae_TB_1_6986",
      "token_next_uri": "ese.json",
      "token_prev_uri": " ge.json",
      "chN": 41
    },
    {
      "index": 33,
      "pos": "Bae_TB_1_7021",
      "token_next_uri": "esc.json",
      "token_prev_uri": " ge.json",
      "chN": 46
    },
    {
      "index": 30,
      "pos": "Bae_TB_1_7162",
      "token_next_uri": "est.json",
      "token_prev_uri": " ge.json",
      "chN": 45
    },
    {
      "index": 12,
      "pos": "Bae_TB_1_7214",
      "token_next_uri": "es .json",
      "token_prev_uri": "nge.json",
      "chN": 15
    },
    {
      "index": 72,
      "pos": "Bae_TB_1_7287",
      "token_next_uri": "esp.json",
      "token_prev_uri": "nge.json",
      "chN": 83
    },
    {
      "index": 1,
      "pos": "Bae_TB_1_7560",
      "token_next_uri": "esc.json",
      "token_prev_uri": " ge.json",
      "chN": 94
    },
    {
      "index": 25,
      "pos": "Bae_TB_1_7619",
      "token_next_uri": "esc.json",
      "token_prev_uri": " ge.json",
      "chN": 67
    },
    {
      "index": 21,
      "pos": "Bae_TB_1_7668",
      "token_next_uri": "esm.json",
      "token_prev_uri": "age.json",
      "chN": 46
    },
    {
      "index": 33,
      "pos": "Bae_TB_1_7668",
      "token_next_uri": "esg.json",
      "token_prev_uri": "age.json",
      "chN": 46
    },
    {
      "index": 36,
      "pos": "Bae_TB_1_7668",
      "token_next_uri": "esc.json",
      "token_prev_uri": "sge.json",
      "chN": 46
    },
    {
      "index": 3,
      "pos": "Bae_TB_1_7677",
      "token_next_uri": "ess.json",
      "token_prev_uri": "age.json",
      "chN": 25
    },
    {
      "index": 1,
      "pos": "Bae_TB_1_7694",
      "token_next_uri": "ese.json",
      "token_prev_uri": " ge.json",
      "chN": 10
    },
    {
      "index": 70,
      "pos": "Bae_TB_1_7769",
      "token_next_uri": "est.json",
      "token_prev_uri": "fge.json",
      "chN": 163
    },
    {
      "index": 223,
      "pos": "Bae_TB_1_8017",
      "token_next_uri": "est.json",
      "token_prev_uri": " ge.json",
      "chN": 279
    },
    {
      "index": 17,
      "pos": "Bae_TB_1_8096",
      "token_next_uri": "esc.json",
      "token_prev_uri": "sge.json",
      "chN": 43
    },
    {
      "index": 130,
      "pos": "Bae_TB_1_8131",
      "token_next_uri": "est.json",
      "token_prev_uri": " ge.json",
      "chN": 998
    },
    {
      "index": 16,
      "pos": "Bae_TB_1_8144",
      "token_next_uri": "ese.json",
      "token_prev_uri": "bge.json",
      "chN": 83
    },
    {
      "index": 592,
      "pos": "Bae_TB_1_8178",
      "token_next_uri": "est.json",
      "token_prev_uri": " ge.json",
      "chN": 895
    },
    {
      "index": 677,
      "pos": "Bae_TB_1_8178",
      "token_next_uri": "esc.json",
      "token_prev_uri": " ge.json",
      "chN": 895
    },
    {
      "index": 240,
      "pos": "Bae_TB_1_8191",
      "token_next_uri": "esa.json",
      "token_prev_uri": "uge.json",
      "chN": 640
    },
    {
      "index": 6,
      "pos": "Bae_TB_1_8301",
      "token_next_uri": "es .json",
      "token_prev_uri": "age.json",
      "chN": 9
    },
    {
      "index": 1751,
      "pos": "Bae_TB_1_8312",
      "token_next_uri": "esc.json",
      "token_prev_uri": "rge.json",
      "chN": 2403
    },
    {
      "index": 1885,
      "pos": "Bae_TB_1_8312",
      "token_next_uri": "esc.json",
      "token_prev_uri": "rge.json",
      "chN": 2403
    },
    {
      "index": 46,
      "pos": "Bae_TB_1_8316",
      "token_next_uri": "est.json",
      "token_prev_uri": "uge.json",
      "chN": 213
    },
    {
      "index": 98,
      "pos": "Bae_TB_1_8449",
      "token_next_uri": "est.json",
      "token_prev_uri": " ge.json",
      "chN": 136
    },
    {
      "index": 186,
      "pos": "Bae_TB_1_8477",
      "token_next_uri": "esc.json",
      "token_prev_uri": " ge.json",
      "chN": 230
    },
    {
      "index": 29,
      "pos": "Bae_TB_1_8634",
      "token_next_uri": "est.json",
      "token_prev_uri": "rge.json",
      "chN": 46
    },
    {
      "index": 43,
      "pos": "Bae_TB_1_8693",
      "token_next_uri": "esc.json",
      "token_prev_uri": " ge.json",
      "chN": 281
    },
    {
      "index": 8,
      "pos": "Bae_TB_1_8725",
      "token_next_uri": "esc.json",
      "token_prev_uri": " ge.json",
      "chN": 63
    },
    {
      "index": 40,
      "pos": "Bae_TB_1_9007",
      "token_next_uri": "ese.json",
      "token_prev_uri": "sge.json",
      "chN": 107
    },
    {
      "index": 19,
      "pos": "Bae_TB_1_9011",
      "token_next_uri": "est.json",
      "token_prev_uri": " ge.json",
      "chN": 83
    },
    {
      "index": 97,
      "pos": "Bae_TB_1_9047",
      "token_next_uri": "esc.json",
      "token_prev_uri": " ge.json",
      "chN": 150
    },
    {
      "index": 63,
      "pos": "Bae_TB_1_9106",
      "token_next_uri": "es .json",
      "token_prev_uri": "ige.json",
      "chN": 174
    },
    {
      "index": 15,
      "pos": "Bae_TB_1_9201",
      "token_next_uri": "ese.json",
      "token_prev_uri": "nge.json",
      "chN": 375
    },
    {
      "index": 99,
      "pos": "Bae_TB_1_9216",
      "token_next_uri": "esc.json",
      "token_prev_uri": " ge.json",
      "chN": 170
    },
    {
      "index": 152,
      "pos": "Bae_TB_1_9225",
      "token_next_uri": "esU+002E.json",
      "token_prev_uri": "ige.json",
      "chN": 178
    },
    {
      "index": 119,
      "pos": "Bae_TB_1_9246",
      "token_next_uri": "est.json",
      "token_prev_uri": " ge.json",
      "chN": 163
    },
    {
      "index": 80,
      "pos": "Bae_TB_1_9253",
      "token_next_uri": "ese.json",
      "token_prev_uri": "sge.json",
      "chN": 188
    },
    {
      "index": 29,
      "pos": "Bae_TB_1_9496",
      "token_next_uri": "ese.json",
      "token_prev_uri": " ge.json",
      "chN": 115
    },
    {
      "index": 123,
      "pos": "Bae_TB_1_9636",
      "token_next_uri": "esc.json",
      "token_prev_uri": " ge.json",
      "chN": 263
    },
    {
      "index": 286,
      "pos": "Bae_TB_1_9685",
      "token_next_uri": "est.json",
      "token_prev_uri": "uge.json",
      "chN": 367
    },
    {
      "index": 334,
      "pos": "Bae_TB_1_9685",
      "token_next_uri": "ese.json",
      "token_prev_uri": "nge.json",
      "chN": 367
    },
    {
      "index": 191,
      "pos": "Bae_TB_1_9755",
      "token_next_uri": "eso.json",
      "token_prev_uri": "age.json",
      "chN": 214
    },
    {
      "index": 56,
      "pos": "Bae_TB_1_9793",
      "token_next_uri": "eso.json",
      "token_prev_uri": "age.json",
      "chN": 82
    },
    {
      "index": 105,
      "pos": "Bae_TB_1_10170",
      "token_next_uri": "esc.json",
      "token_prev_uri": "nge.json",
      "chN": 287
    },
    {
      "index": 125,
      "pos": "Bae_TB_1_10282",
      "token_next_uri": "esi.json",
      "token_prev_uri": " ge.json",
      "chN": 419
    },
    {
      "index": 137,
      "pos": "Bae_TB_1_10308",
      "token_next_uri": "est.json",
      "token_prev_uri": "sge.json",
      "chN": 215
    },
    {
      "index": 244,
      "pos": "Bae_TB_1_10321",
      "token_next_uri": "es,.json",
      "token_prev_uri": "ige.json",
      "chN": 394
    },
    {
      "index": 336,
      "pos": "Bae_TB_1_10328",
      "token_next_uri": "es,.json",
      "token_prev_uri": "ige.json",
      "chN": 552
    },
    {
      "index": 83,
      "pos": "Bae_TB_1_10334",
      "token_next_uri": "ese.json",
      "token_prev_uri": "mge.json",
      "chN": 625
    },
    {
      "index": 94,
      "pos": "Bae_TB_1_10353",
      "token_next_uri": "esp.json",
      "token_prev_uri": "sge.json",
      "chN": 130
    },
    {
      "index": 1041,
      "pos": "Bae_TB_1_10357",
      "token_next_uri": "esc.json",
      "token_prev_uri": " ge.json",
      "chN": 1228
    },
    {
      "index": 92,
      "pos": "Bae_TB_1_10400",
      "token_next_uri": "ese.json",
      "token_prev_uri": " ge.json",
      "chN": 528
    },
    {
      "index": 30,
      "pos": "Bae_TB_1_10403",
      "token_next_uri": "ese.json",
      "token_prev_uri": "zge.json",
      "chN": 179
    },
    {
      "index": 63,
      "pos": "Bae_TB_1_10403",
      "token_next_uri": "est.json",
      "token_prev_uri": " ge.json",
      "chN": 179
    },
    {
      "index": 47,
      "pos": "Bae_TB_1_10418",
      "token_next_uri": "es .json",
      "token_prev_uri": "ege.json",
      "chN": 535
    },
    {
      "index": 446,
      "pos": "Bae_TB_1_10418",
      "token_next_uri": "ese.json",
      "token_prev_uri": "nge.json",
      "chN": 535
    },
    {
      "index": 192,
      "pos": "Bae_TB_1_10453",
      "token_next_uri": "esu.json",
      "token_prev_uri": " ge.json",
      "chN": 301
    },
    {
      "index": 75,
      "pos": "Bae_TB_1_10485",
      "token_next_uri": "ese.json",
      "token_prev_uri": "nge.json",
      "chN": 92
    },
    {
      "index": 141,
      "pos": "Bae_TB_1_10498",
      "token_next_uri": "esc.json",
      "token_prev_uri": " ge.json",
      "chN": 358
    },
    {
      "index": 70,
      "pos": "Bae_TB_1_10514",
      "token_next_uri": "ese.json",
      "token_prev_uri": "nge.json",
      "chN": 194
    },
    {
      "index": 43,
      "pos": "Bae_TB_1_10521",
      "token_next_uri": "est.json",
      "token_prev_uri": " ge.json",
      "chN": 72
    },
    {
      "index": 23,
      "pos": "Bae_TB_1_10529",
      "token_next_uri": "ese.json",
      "token_prev_uri": " ge.json",
      "chN": 384
    },
    {
      "index": 241,
      "pos": "Bae_TB_1_10529",
      "token_next_uri": "ese.json",
      "token_prev_uri": "dge.json",
      "chN": 384
    },
    {
      "index": 3,
      "pos": "Bae_TB_1_10543",
      "token_next_uri": "esc.json",
      "token_prev_uri": "nge.json",
      "chN": 218
    },
    {
      "index": 8,
      "pos": "Bae_TB_1_10813",
      "token_next_uri": "ese.json",
      "token_prev_uri": " ge.json",
      "chN": 21
    },
    {
      "index": 32,
      "pos": "Bae_TB_1_10855",
      "token_next_uri": "esc.json",
      "token_prev_uri": " ge.json",
      "chN": 71
    },
    {
      "index": 40,
      "pos": "Bae_TB_1_10936",
      "token_next_uri": "esc.json",
      "token_prev_uri": "nge.json",
      "chN": 53
    },
    {
      "index": 78,
      "pos": "Bae_TB_1_10978",
      "token_next_uri": "esc.json",
      "token_prev_uri": "rge.json",
      "chN": 98
    },
    {
      "index": 144,
      "pos": "Bae_TB_1_11240",
      "token_next_uri": "esp.json",
      "token_prev_uri": " ge.json",
      "chN": 154
    },
    {
      "index": 68,
      "pos": "Bae_TB_1_11319",
      "token_next_uri": "ese.json",
      "token_prev_uri": "tge.json",
      "chN": 89
    },
    {
      "index": 575,
      "pos": "Bae_TB_1_11336",
      "token_next_uri": "esi.json",
      "token_prev_uri": "nge.json",
      "chN": 629
    },
    {
      "index": 294,
      "pos": "Bae_TB_1_11429",
      "token_next_uri": "es .json",
      "token_prev_uri": "age.json",
      "chN": 847
    },
    {
      "index": 54,
      "pos": "Bae_TB_1_11461",
      "token_next_uri": "esc.json",
      "token_prev_uri": "uge.json",
      "chN": 72
    },
    {
      "index": 159,
      "pos": "Bae_TB_1_11552",
      "token_next_uri": "es .json",
      "token_prev_uri": "ige.json",
      "chN": 341
    },
    {
      "index": 29,
      "pos": "Bae_TB_1_11555",
      "token_next_uri": "es .json",
      "token_prev_uri": "ige.json",
      "chN": 220
    },
    {
      "index": 19,
      "pos": "Bae_TB_1_11580",
      "token_next_uri": "esc.json",
      "token_prev_uri": " ge.json",
      "chN": 92
    },
    {
      "index": 1,
      "pos": "Bae_TB_1_11592",
      "token_next_uri": "ese.json",
      "token_prev_uri": " ge.json",
      "chN": 30
    },
    {
      "index": 71,
      "pos": "Bae_TB_1_11635",
      "token_next_uri": "esc.json",
      "token_prev_uri": " ge.json",
      "chN": 245
    },
    {
      "index": 171,
      "pos": "Bae_TB_1_11635",
      "token_next_uri": "esc.json",
      "token_prev_uri": "bge.json",
      "chN": 245
    },
    {
      "index": 40,
      "pos": "Bae_TB_1_11652",
      "token_next_uri": "esa.json",
      "token_prev_uri": " ge.json",
      "chN": 126
    },
    {
      "index": 24,
      "pos": "Bae_TB_1_11752",
      "token_next_uri": "esc.json",
      "token_prev_uri": " ge.json",
      "chN": 70
    },
    {
      "index": 166,
      "pos": "Bae_TB_1_11874",
      "token_next_uri": "esc.json",
      "token_prev_uri": "nge.json",
      "chN": 230
    },
    {
      "index": 131,
      "pos": "Bae_TB_1_11991",
      "token_next_uri": "est.json",
      "token_prev_uri": "fge.json",
      "chN": 425
    },
    {
      "index": 40,
      "pos": "Bae_TB_1_12089",
      "token_next_uri": "ese.json",
      "token_prev_uri": "rge.json",
      "chN": 49
    },
    {
      "index": 81,
      "pos": "Bae_TB_1_12189",
      "token_next_uri": "esc.json",
      "token_prev_uri": "sge.json",
      "chN": 99
    },
    {
      "index": 152,
      "pos": "Bae_TB_1_12334",
      "token_next_uri": "est.json",
      "token_prev_uri": " ge.json",
      "chN": 548
    },
    {
      "index": 361,
      "pos": "Bae_TB_1_12334",
      "token_next_uri": "es .json",
      "token_prev_uri": "age.json",
      "chN": 548
    },
    {
      "index": 444,
      "pos": "Bae_TB_1_12334",
      "token_next_uri": "esc.json",
      "token_prev_uri": "rge.json",
      "chN": 548
    },
    {
      "index": 92,
      "pos": "Bae_TB_1_12369",
      "token_next_uri": "est.json",
      "token_prev_uri": " ge.json",
      "chN": 125
    },
    {
      "index": 13,
      "pos": "Bae_TB_1_12414",
      "token_next_uri": "esc.json",
      "token_prev_uri": " ge.json",
      "chN": 511
    },
    {
      "index": 28,
      "pos": "Bae_TB_1_12712",
      "token_next_uri": "esp.json",
      "token_prev_uri": " ge.json",
      "chN": 136
    },
    {
      "index": 404,
      "pos": "Bae_TB_1_12889",
      "token_next_uri": "ese.json",
      "token_prev_uri": " ge.json",
      "chN": 1020
    },
    {
      "index": 530,
      "pos": "Bae_TB_1_12889",
      "token_next_uri": "es .json",
      "token_prev_uri": "ige.json",
      "chN": 1020
    },
    {
      "index": 403,
      "pos": "Bae_TB_1_12893",
      "token_next_uri": "ese.json",
      "token_prev_uri": "bge.json",
      "chN": 498
    },
    {
      "index": 207,
      "pos": "Bae_TB_1_12902",
      "token_next_uri": "esä.json",
      "token_prev_uri": "nge.json",
      "chN": 230
    },
    {
      "index": 55,
      "pos": "Bae_TB_1_13045",
      "token_next_uri": "esc.json",
      "token_prev_uri": " ge.json",
      "chN": 71
    },
    {
      "index": 14,
      "pos": "Bae_TB_1_13058",
      "token_next_uri": "es .json",
      "token_prev_uri": "ige.json",
      "chN": 101
    },
    {
      "index": 23,
      "pos": "Bae_TB_1_13088",
      "token_next_uri": "ese.json",
      "token_prev_uri": " ge.json",
      "chN": 513
    },
    {
      "index": 165,
      "pos": "Bae_TB_1_13151",
      "token_next_uri": "ese.json",
      "token_prev_uri": "rge.json",
      "chN": 178
    },
    {
      "index": 12,
      "pos": "Bae_TB_1_13180",
      "token_next_uri": "esc.json",
      "token_prev_uri": "sge.json",
      "chN": 78
    },
    {
      "index": 61,
      "pos": "Bae_TB_1_13180",
      "token_next_uri": "esc.json",
      "token_prev_uri": " ge.json",
      "chN": 78
    },
    {
      "index": 201,
      "pos": "Bae_TB_1_13192",
      "token_next_uri": "est.json",
      "token_prev_uri": " ge.json",
      "chN": 409
    },
    {
      "index": 11,
      "pos": "Bae_TB_1_13243",
      "token_next_uri": "ese.json",
      "token_prev_uri": " ge.json",
      "chN": 404
    },
    {
      "index": 17,
      "pos": "Bae_TB_1_13251",
      "token_next_uri": "esc.json",
      "token_prev_uri": " ge.json",
      "chN": 60
    },
    {
      "index": 18,
      "pos": "Bae_TB_1_13323",
      "token_next_uri": "esc.json",
      "token_prev_uri": "nge.json",
      "chN": 134
    },
    {
      "index": 3,
      "pos": "Bae_TB_1_13466",
      "token_next_uri": "est.json",
      "token_prev_uri": "uge.json",
      "chN": 179
    },
    {
      "index": 142,
      "pos": "Bae_TB_1_13466",
      "token_next_uri": "esc.json",
      "token_prev_uri": " ge.json",
      "chN": 179
    },
    {
      "index": 32,
      "pos": "Bae_TB_1_13571",
      "token_next_uri": "ese.json",
      "token_prev_uri": " ge.json",
      "chN": 108
    },
    {
      "index": 28,
      "pos": "Bae_TB_1_13834",
      "token_next_uri": "esi.json",
      "token_prev_uri": "nge.json",
      "chN": 313
    },
    {
      "index": 242,
      "pos": "Bae_TB_1_13834",
      "token_next_uri": "esp.json",
      "token_prev_uri": "sge.json",
      "chN": 313
    },
    {
      "index": 303,
      "pos": "Bae_TB_1_13834",
      "token_next_uri": "esa.json",
      "token_prev_uri": " ge.json",
      "chN": 313
    },
    {
      "index": 1,
      "pos": "Bae_TB_1_13847",
      "token_next_uri": "esc.json",
      "token_prev_uri": " ge.json",
      "chN": 521
    },
    {
      "index": 188,
      "pos": "Bae_TB_1_13847",
      "token_next_uri": "est.json",
      "token_prev_uri": " ge.json",
      "chN": 521
    },
    {
      "index": 390,
      "pos": "Bae_TB_1_13847",
      "token_next_uri": "esb.json",
      "token_prev_uri": "ege.json",
      "chN": 521
    },
    {
      "index": 51,
      "pos": "Bae_TB_1_13898",
      "token_next_uri": "esc.json",
      "token_prev_uri": "nge.json",
      "chN": 111
    },
    {
      "index": 37,
      "pos": "Bae_TB_1_13909",
      "token_next_uri": "esc.json",
      "token_prev_uri": "sge.json",
      "chN": 50
    },
    {
      "index": 85,
      "pos": "Bae_TB_1_13955",
      "token_next_uri": "esc.json",
      "token_prev_uri": " ge.json",
      "chN": 329
    },
    {
      "index": 84,
      "pos": "Bae_TB_1_13974",
      "token_next_uri": "esc.json",
      "token_prev_uri": " ge.json",
      "chN": 615
    },
    {
      "index": 48,
      "pos": "Bae_TB_1_14025",
      "token_next_uri": "esp.json",
      "token_prev_uri": "sge.json",
      "chN": 98
    },
    {
      "index": 134,
      "pos": "Bae_TB_1_14452",
      "token_next_uri": "est.json",
      "token_prev_uri": "tge.json",
      "chN": 310
    },
    {
      "index": 231,
      "pos": "Bae_TB_1_14452",
      "token_next_uri": "esi.json",
      "token_prev_uri": "nge.json",
      "chN": 310
    },
    {
      "index": 53,
      "pos": "Bae_TB_1_14468",
      "token_next_uri": "esc.json",
      "token_prev_uri": "nge.json",
      "chN": 428
    },
    {
      "index": 153,
      "pos": "Bae_TB_1_14468",
      "token_next_uri": "ese.json",
      "token_prev_uri": " ge.json",
      "chN": 428
    },
    {
      "index": 253,
      "pos": "Bae_TB_1_14472",
      "token_next_uri": "es .json",
      "token_prev_uri": "üge.json",
      "chN": 320
    },
    {
      "index": 112,
      "pos": "Bae_TB_1_14475",
      "token_next_uri": "est.json",
      "token_prev_uri": " ge.json",
      "chN": 212
    },
    {
      "index": 264,
      "pos": "Bae_TB_1_14491",
      "token_next_uri": "ese.json",
      "token_prev_uri": "dge.json",
      "chN": 457
    },
    {
      "index": 76,
      "pos": "Bae_TB_1_14498",
      "token_next_uri": "esc.json",
      "token_prev_uri": " ge.json",
      "chN": 727
    },
    {
      "index": 546,
      "pos": "Bae_TB_1_14498",
      "token_next_uri": "ese.json",
      "token_prev_uri": " ge.json",
      "chN": 727
    },
    {
      "index": 209,
      "pos": "Bae_TB_1_14509",
      "token_next_uri": "esi.json",
      "token_prev_uri": " ge.json",
      "chN": 451
    },
    {
      "index": 65,
      "pos": "Bae_TB_1_14522",
      "token_next_uri": "esc.json",
      "token_prev_uri": "fge.json",
      "chN": 234
    },
    {
      "index": 59,
      "pos": "Bae_TB_1_14616",
      "token_next_uri": "ese.json",
      "token_prev_uri": "fge.json",
      "chN": 104
    },
    {
      "index": 1,
      "pos": "Bae_TB_1_14917",
      "token_next_uri": "esp.json",
      "token_prev_uri": " ge.json",
      "chN": 91
    },
    {
      "index": 81,
      "pos": "Bae_TB_1_14973",
      "token_next_uri": "esc.json",
      "token_prev_uri": "sge.json",
      "chN": 153
    },
    {
      "index": 20,
      "pos": "Bae_TB_1_15038",
      "token_next_uri": "esü.json",
      "token_prev_uri": " ge.json",
      "chN": 31
    },
    {
      "index": 44,
      "pos": "Bae_TB_1_15062",
      "token_next_uri": "esc.json",
      "token_prev_uri": " ge.json",
      "chN": 87
    },
    {
      "index": 517,
      "pos": "Bae_TB_1_15101",
      "token_next_uri": "est.json",
      "token_prev_uri": " ge.json",
      "chN": 594
    },
    {
      "index": 86,
      "pos": "Bae_TB_1_15104",
      "token_next_uri": "est.json",
      "token_prev_uri": "fge.json",
      "chN": 116
    },
    {
      "index": 59,
      "pos": "Bae_TB_1_15131",
      "token_next_uri": "esc.json",
      "token_prev_uri": " ge.json",
      "chN": 79
    },
    {
      "index": 497,
      "pos": "Bae_TB_1_15134",
      "token_next_uri": "esc.json",
      "token_prev_uri": "bge.json",
      "chN": 627
    },
    {
      "index": 65,
      "pos": "Bae_TB_1_15165",
      "token_next_uri": "est.json",
      "token_prev_uri": " ge.json",
      "chN": 120
    },
    {
      "index": 42,
      "pos": "Bae_TB_1_15169",
      "token_next_uri": "esc.json",
      "token_prev_uri": "sge.json",
      "chN": 58
    },
    {
      "index": 108,
      "pos": "Bae_TB_1_15190",
      "token_next_uri": "est.json",
      "token_prev_uri": "nge.json",
      "chN": 200
    },
    {
      "index": 339,
      "pos": "Bae_TB_1_15268",
      "token_next_uri": "est.json",
      "token_prev_uri": "nge.json",
      "chN": 348
    },
    {
      "index": 233,
      "pos": "Bae_TB_1_15277",
      "token_next_uri": "est.json",
      "token_prev_uri": " ge.json",
      "chN": 290
    },
    {
      "index": 44,
      "pos": "Bae_TB_1_15281",
      "token_next_uri": "est.json",
      "token_prev_uri": " ge.json",
      "chN": 67
    },
    {
      "index": 144,
      "pos": "Bae_TB_1_15306",
      "token_next_uri": "ese.json",
      "token_prev_uri": "bge.json",
      "chN": 175
    },
    {
      "index": 33,
      "pos": "Bae_TB_1_15338",
      "token_next_uri": "esp.json",
      "token_prev_uri": " ge.json",
      "chN": 103
    },
    {
      "index": 26,
      "pos": "Bae_TB_1_15346",
      "token_next_uri": "ese.json",
      "token_prev_uri": "bge.json",
      "chN": 171
    },
    {
      "index": 55,
      "pos": "Bae_TB_1_15616",
      "token_next_uri": "est.json",
      "token_prev_uri": " ge.json",
      "chN": 213
    },
    {
      "index": 32,
      "pos": "Bae_TB_1_15649",
      "token_next_uri": "ess.json",
      "token_prev_uri": "age.json",
      "chN": 83
    },
    {
      "index": 12,
      "pos": "Bae_TB_1_15679",
      "token_next_uri": "esa.json",
      "token_prev_uri": " ge.json",
      "chN": 84
    },
    {
      "index": 1,
      "pos": "Bae_TB_1_15683",
      "token_next_uri": "ese.json",
      "token_prev_uri": " ge.json",
      "chN": 40
    },
    {
      "index": 55,
      "pos": "Bae_TB_1_15776",
      "token_next_uri": "est.json",
      "token_prev_uri": " ge.json",
      "chN": 83
    },
    {
      "index": 14,
      "pos": "Bae_TB_1_15811",
      "token_next_uri": "ese.json",
      "token_prev_uri": "sge.json",
      "chN": 111
    },
    {
      "index": 25,
      "pos": "Bae_TB_1_15814",
      "token_next_uri": "ese.json",
      "token_prev_uri": "sge.json",
      "chN": 48
    },
    {
      "index": 73,
      "pos": "Bae_TB_1_15827",
      "token_next_uri": "ese.json",
      "token_prev_uri": "sge.json",
      "chN": 112
    },
    {
      "index": 14,
      "pos": "Bae_TB_1_15833",
      "token_next_uri": "ese.json",
      "token_prev_uri": "sge.json",
      "chN": 59
    },
    {
      "index": 13,
      "pos": "Bae_TB_1_15844",
      "token_next_uri": "ese.json",
      "token_prev_uri": "sge.json",
      "chN": 88
    },
    {
      "index": 13,
      "pos": "Bae_TB_1_15847",
      "token_next_uri": "ese.json",
      "token_prev_uri": "sge.json",
      "chN": 68
    },
    {
      "index": 6,
      "pos": "Bae_TB_1_15860",
      "token_next_uri": "es,.json",
      "token_prev_uri": "age.json",
      "chN": 9
    },
    {
      "index": 35,
      "pos": "Bae_TB_1_15902",
      "token_next_uri": "est.json",
      "token_prev_uri": "mge.json",
      "chN": 45
    },
    {
      "index": 165,
      "pos": "Bae_TB_1_15986",
      "token_next_uri": "esa.json",
      "token_prev_uri": "bge.json",
      "chN": 179
    },
    {
      "index": 91,
      "pos": "Bae_TB_1_16020",
      "token_next_uri": "esc.json",
      "token_prev_uri": " ge.json",
      "chN": 116
    },
    {
      "index": 174,
      "pos": "Bae_TB_1_16028",
      "token_next_uri": "esc.json",
      "token_prev_uri": " ge.json",
      "chN": 232
    },
    {
      "index": 174,
      "pos": "Bae_TB_1_16032",
      "token_next_uri": "esp.json",
      "token_prev_uri": "sge.json",
      "chN": 358
    },
    {
      "index": 6,
      "pos": "Bae_TB_1_16071",
      "token_next_uri": "es .json",
      "token_prev_uri": "age.json",
      "chN": 9
    },
    {
      "index": 157,
      "pos": "Bae_TB_1_16177",
      "token_next_uri": "esa.json",
      "token_prev_uri": " ge.json",
      "chN": 321
    },
    {
      "index": 16,
      "pos": "Bae_TB_1_16244",
      "token_next_uri": "es .json",
      "token_prev_uri": "ige.json",
      "chN": 41
    },
    {
      "index": 93,
      "pos": "Bae_TB_1_16286",
      "token_next_uri": "esc.json",
      "token_prev_uri": "fge.json",
      "chN": 118
    },
    {
      "index": 38,
      "pos": "Bae_TB_1_16327",
      "token_next_uri": "esc.json",
      "token_prev_uri": "tge.json",
      "chN": 121
    },
    {
      "index": 144,
      "pos": "Bae_TB_1_16375",
      "token_next_uri": "es .json",
      "token_prev_uri": "ige.json",
      "chN": 239
    },
    {
      "index": 160,
      "pos": "Bae_TB_1_16375",
      "token_next_uri": "es .json",
      "token_prev_uri": "ige.json",
      "chN": 239
    },
    {
      "index": 159,
      "pos": "Bae_TB_1_16400",
      "token_next_uri": "esc.json",
      "token_prev_uri": "tge.json",
      "chN": 218
    },
    {
      "index": 11,
      "pos": "Bae_TB_1_16404",
      "token_next_uri": "esc.json",
      "token_prev_uri": "tge.json",
      "chN": 65
    },
    {
      "index": 9,
      "pos": "Bae_TB_1_16765",
      "token_next_uri": "esc.json",
      "token_prev_uri": " ge.json",
      "chN": 64
    }
  ]
}