{
  "token": "hU+002E ",
  "instances": [
    {
      "index": 162,
      "pos": "Bae_MF_1_501",
      "token_next_uri": "U+002E N.json",
      "token_prev_uri": "chU+002E.json",
      "chN": 170
    },
    {
      "index": 188,
      "pos": "Bae_MF_1_856",
      "token_next_uri": "U+002E I.json",
      "token_prev_uri": "chU+002E.json",
      "chN": 191
    },
    {
      "index": 178,
      "pos": "Bae_MF_1_1272",
      "token_next_uri": "U+002E I.json",
      "token_prev_uri": "chU+002E.json",
      "chN": 181
    },
    {
      "index": 18,
      "pos": "Bae_MF_1_1505",
      "token_next_uri": "U+002E M.json",
      "token_prev_uri": "chU+002E.json",
      "chN": 88
    },
    {
      "index": 183,
      "pos": "Bae_MF_1_1788",
      "token_next_uri": "U+002E A.json",
      "token_prev_uri": "chU+002E.json",
      "chN": 220
    },
    {
      "index": 1,
      "pos_pr": "Bae_MF_1_2173",
      "pos_nxt": "Bae_MF_1_2175",
      "token_next_uri": "U+002E S.json",
      "token_prev_uri": "chU+002E.json",
      "chN": 4
    },
    {
      "index": 115,
      "pos": "Bae_MF_1_2181",
      "token_next_uri": "U+002E A.json",
      "token_prev_uri": "chU+002E.json",
      "chN": 668
    },
    {
      "index": 97,
      "pos": "Bae_MF_1_2374",
      "token_next_uri": "U+002E I.json",
      "token_prev_uri": "chU+002E.json",
      "chN": 100
    },
    {
      "index": 48,
      "pos": "Bae_MF_1_3242",
      "token_next_uri": "U+002E I.json",
      "token_prev_uri": "chU+002E.json",
      "chN": 383
    },
    {
      "index": 6,
      "pos": "Bae_MF_1_3559",
      "token_next_uri": "U+002E B.json",
      "token_prev_uri": "chU+002E.json",
      "chN": 144
    },
    {
      "index": 32,
      "pos": "Bae_MF_1_3574",
      "token_next_uri": "U+002E I.json",
      "token_prev_uri": "chU+002E.json",
      "chN": 95
    },
    {
      "index": 266,
      "pos": "Bae_MF_1_3630",
      "token_next_uri": "U+002E S.json",
      "token_prev_uri": "chU+002E.json",
      "chN": 440
    },
    {
      "index": 155,
      "pos": "Bae_MF_1_4397",
      "token_next_uri": "U+002E D.json",
      "token_prev_uri": "chU+002E.json",
      "chN": 158
    },
    {
      "index": 26,
      "pos": "Bae_MF_1_5144",
      "token_next_uri": "U+002E D.json",
      "token_prev_uri": "chU+002E.json",
      "chN": 33
    },
    {
      "index": 34,
      "pos": "Bae_MF_1_5276",
      "token_next_uri": "U+002E A.json",
      "token_prev_uri": "chU+002E.json",
      "chN": 135
    },
    {
      "index": 189,
      "pos": "Bae_MF_1_5321",
      "token_next_uri": "U+002E W.json",
      "token_prev_uri": "ahU+002E.json",
      "chN": 336
    },
    {
      "index": 16,
      "pos": "Bae_MF_1_5523",
      "token_next_uri": "U+002E D.json",
      "token_prev_uri": "thU+002E.json",
      "chN": 31
    },
    {
      "index": 11,
      "pos": "Bae_MF_1_5864",
      "token_next_uri": "U+002E A.json",
      "token_prev_uri": "chU+002E.json",
      "chN": 17
    },
    {
      "index": 213,
      "pos": "Bae_MF_1_6475",
      "token_next_uri": "U+002E D.json",
      "token_prev_uri": "chU+002E.json",
      "chN": 395
    },
    {
      "index": 141,
      "pos": "Bae_MF_1_6776",
      "token_next_uri": "U+002E S.json",
      "token_prev_uri": "chU+002E.json",
      "chN": 144
    },
    {
      "index": 12,
      "pos": "Bae_MF_1_6822",
      "token_next_uri": "U+002E L.json",
      "token_prev_uri": "chU+002E.json",
      "chN": 91
    },
    {
      "index": 141,
      "pos": "Bae_MF_1_6993",
      "token_next_uri": "U+002E A.json",
      "token_prev_uri": "chU+002E.json",
      "chN": 376
    },
    {
      "index": 338,
      "pos": "Bae_MF_1_6993",
      "token_next_uri": "U+002E D.json",
      "token_prev_uri": "chU+002E.json",
      "chN": 376
    },
    {
      "index": 282,
      "pos": "Bae_MF_1_8028",
      "token_next_uri": "U+002E B.json",
      "token_prev_uri": "chU+002E.json",
      "chN": 319
    },
    {
      "index": 17,
      "pos": "Bae_MF_1_8376",
      "token_next_uri": "U+002E N.json",
      "token_prev_uri": "chU+002E.json",
      "chN": 111
    },
    {
      "index": 103,
      "pos": "Bae_MF_1_8561",
      "token_next_uri": "U+002E H.json",
      "token_prev_uri": "chU+002E.json",
      "chN": 116
    },
    {
      "index": 78,
      "pos": "Bae_MF_1_8593",
      "token_next_uri": "U+002E V.json",
      "token_prev_uri": "ahU+002E.json",
      "chN": 187
    },
    {
      "index": 63,
      "pos": "Bae_MF_1_8767",
      "token_next_uri": "U+002E U.json",
      "token_prev_uri": "chU+002E.json",
      "chN": 66
    },
    {
      "index": 43,
      "pos": "Bae_MF_1_9520",
      "token_next_uri": "U+002E Z.json",
      "token_prev_uri": "chU+002E.json",
      "chN": 101
    },
    {
      "index": 112,
      "pos": "Bae_MF_1_9586",
      "token_next_uri": "U+002E E.json",
      "token_prev_uri": "chU+002E.json",
      "chN": 195
    },
    {
      "index": 125,
      "pos": "Bae_MF_1_9676",
      "token_next_uri": "U+002E W.json",
      "token_prev_uri": "chU+002E.json",
      "chN": 128
    },
    {
      "index": 44,
      "pos": "Bae_MF_1_9866",
      "token_next_uri": "U+002E W.json",
      "token_prev_uri": "chU+002E.json",
      "chN": 255
    },
    {
      "index": 58,
      "pos": "Bae_MF_1_10366",
      "token_next_uri": "U+002E E.json",
      "token_prev_uri": "chU+002E.json",
      "chN": 110
    },
    {
      "index": 1,
      "pos_pr": "Bae_MF_2_824",
      "pos_nxt": "Bae_MF_2_826",
      "token_next_uri": "U+002E I.json",
      "token_prev_uri": "thU+002E.json",
      "chN": 4
    },
    {
      "index": 249,
      "pos": "Bae_MF_2_1983",
      "token_next_uri": "U+002E I.json",
      "token_prev_uri": "chU+002E.json",
      "chN": 433
    },
    {
      "index": 124,
      "pos": "Bae_MF_2_2022",
      "token_next_uri": "U+002E U.json",
      "token_prev_uri": "chU+002E.json",
      "chN": 173
    },
    {
      "index": 23,
      "pos": "Bae_MF_2_2222",
      "token_next_uri": "U+002E D.json",
      "token_prev_uri": "chU+002E.json",
      "chN": 1012
    },
    {
      "index": 54,
      "pos": "Bae_MF_2_2584",
      "token_next_uri": "U+002E W.json",
      "token_prev_uri": "chU+002E.json",
      "chN": 101
    },
    {
      "index": 226,
      "pos": "Bae_MF_2_2739",
      "token_next_uri": "U+002E N.json",
      "token_prev_uri": "chU+002E.json",
      "chN": 371
    },
    {
      "index": 6,
      "pos": "Bae_MF_2_3024",
      "token_next_uri": "U+002E I.json",
      "token_prev_uri": "chU+002E.json",
      "chN": 12
    },
    {
      "index": 68,
      "pos": "Bae_MF_2_3995",
      "token_next_uri": "U+002E E.json",
      "token_prev_uri": "chU+002E.json",
      "chN": 76
    },
    {
      "index": 149,
      "pos": "Bae_MF_2_4829",
      "token_next_uri": "U+002E O.json",
      "token_prev_uri": "ahU+002E.json",
      "chN": 244
    },
    {
      "index": 4,
      "pos": "Bae_MF_2_5204",
      "token_next_uri": "U+002E I.json",
      "token_prev_uri": "chU+002E.json",
      "chN": 102
    },
    {
      "index": 7,
      "pos": "Bae_MF_2_5346",
      "token_next_uri": "U+002E D.json",
      "token_prev_uri": "chU+002E.json",
      "chN": 66
    },
    {
      "index": 161,
      "pos": "Bae_MF_2_7496",
      "token_next_uri": "U+002E D.json",
      "token_prev_uri": "chU+002E.json",
      "chN": 164
    },
    {
      "index": 123,
      "pos": "Bae_MF_2_8470",
      "token_next_uri": "U+002E I.json",
      "token_prev_uri": "chU+002E.json",
      "chN": 321
    },
    {
      "index": 212,
      "pos": "Bae_MF_2_8470",
      "token_next_uri": "U+002E D.json",
      "token_prev_uri": "chU+002E.json",
      "chN": 321
    },
    {
      "index": 32,
      "pos": "Bae_MF_2_8594",
      "token_next_uri": "U+002E D.json",
      "token_prev_uri": "chU+002E.json",
      "chN": 111
    },
    {
      "index": 5,
      "pos": "Bae_MF_2_9282",
      "token_next_uri": "U+002E E.json",
      "token_prev_uri": "chU+002E.json",
      "chN": 8
    },
    {
      "index": 23,
      "pos": "Bae_MF_2_10013",
      "token_next_uri": "U+002E A.json",
      "token_prev_uri": "chU+002E.json",
      "chN": 31
    },
    {
      "index": 277,
      "pos": "Bae_MF_2_10982",
      "token_next_uri": "U+002E D.json",
      "token_prev_uri": "chU+002E.json",
      "chN": 284
    },
    {
      "index": 311,
      "pos": "Bae_MF_2_11677",
      "token_next_uri": "U+002E D.json",
      "token_prev_uri": "chU+002E.json",
      "chN": 355
    },
    {
      "index": 64,
      "pos": "Bae_MF_2_12213",
      "token_next_uri": "U+002E G.json",
      "token_prev_uri": "chU+002E.json",
      "chN": 81
    },
    {
      "index": 38,
      "pos": "Bae_MF_6-1_286",
      "token_next_uri": "U+002E  .json",
      "token_prev_uri": "chU+002E.json",
      "chN": 41
    },
    {
      "index": 1,
      "pos_pr": "Bae_MF_6-1_1041",
      "pos_nxt": "Bae_MF_6-1_1043",
      "token_next_uri": "U+002E M.json",
      "token_prev_uri": "chU+002E.json",
      "chN": 4
    },
    {
      "index": 1,
      "pos_pr": "Bae_MF_6-1_1067",
      "pos_nxt": "Bae_MF_6-1_1069",
      "token_next_uri": "U+002E S.json",
      "token_prev_uri": "chU+002E.json",
      "chN": 4
    },
    {
      "index": 1,
      "pos_pr": "Bae_MF_6-1_1436",
      "pos_nxt": "Bae_MF_6-1_1438",
      "token_next_uri": "U+002E  .json",
      "token_prev_uri": "chU+002E.json",
      "chN": 4
    },
    {
      "index": 384,
      "pos": "Bae_MF_6-1_1852",
      "token_next_uri": "U+002E P.json",
      "token_prev_uri": "chU+002E.json",
      "chN": 387
    },
    {
      "index": 302,
      "pos": "Bae_MF_6-1_2145",
      "token_next_uri": "U+002E R.json",
      "token_prev_uri": "chU+002E.json",
      "chN": 305
    },
    {
      "index": 136,
      "pos": "Bae_MF_6-1_2183",
      "token_next_uri": "U+002E N.json",
      "token_prev_uri": "chU+002E.json",
      "chN": 196
    },
    {
      "index": 70,
      "pos": "Bae_MF_6-1_2227",
      "token_next_uri": "U+002E i.json",
      "token_prev_uri": " hU+002E.json",
      "chN": 480
    },
    {
      "index": 1,
      "pos_pr": "Bae_MF_6-1_2591",
      "pos_nxt": "Bae_MF_6-1_2597",
      "token_next_uri": "U+002E E.json",
      "token_prev_uri": "chU+002E.json",
      "chN": 4
    },
    {
      "index": 31,
      "pos": "Bae_MF_6-1_3028",
      "token_next_uri": "U+002E O.json",
      "token_prev_uri": "chU+002E.json",
      "chN": 69
    },
    {
      "index": 8,
      "pos": "Bae_MF_6-1_3044",
      "token_next_uri": "U+002E E.json",
      "token_prev_uri": "chU+002E.json",
      "chN": 11
    },
    {
      "index": 27,
      "pos": "Bae_MF_6-1_4217",
      "token_next_uri": "U+002E U.json",
      "token_prev_uri": "chU+002E.json",
      "chN": 54
    },
    {
      "index": 194,
      "pos": "Bae_MF_6-1_4396",
      "token_next_uri": "U+002E A.json",
      "token_prev_uri": "chU+002E.json",
      "chN": 565
    },
    {
      "index": 97,
      "pos": "Bae_MF_6-1_4542",
      "token_next_uri": "U+002E A.json",
      "token_prev_uri": "chU+002E.json",
      "chN": 205
    },
    {
      "index": 25,
      "pos": "Bae_MF_6-1_4710",
      "token_next_uri": "U+002E S.json",
      "token_prev_uri": "chU+002E.json",
      "chN": 28
    },
    {
      "index": 13,
      "pos": "Bae_MF_6-1_4819",
      "token_next_uri": "U+002E J.json",
      "token_prev_uri": "chU+002E.json",
      "chN": 108
    },
    {
      "index": 44,
      "pos": "Bae_MF_6-1_4819",
      "token_next_uri": "U+002E M.json",
      "token_prev_uri": "chU+002E.json",
      "chN": 108
    },
    {
      "index": 8,
      "pos": "Bae_MF_6-1_4821",
      "token_next_uri": "U+002E E.json",
      "token_prev_uri": "chU+002E.json",
      "chN": 29
    },
    {
      "index": 71,
      "pos": "Bae_MF_6-1_4962",
      "token_next_uri": "U+002E I.json",
      "token_prev_uri": "chU+002E.json",
      "chN": 105
    },
    {
      "index": 8,
      "pos": "Bae_MF_6-1_5070",
      "token_next_uri": "U+002E I.json",
      "token_prev_uri": "chU+002E.json",
      "chN": 106
    },
    {
      "index": 70,
      "pos": "Bae_MF_6-1_5070",
      "token_next_uri": "U+002E D.json",
      "token_prev_uri": "chU+002E.json",
      "chN": 106
    },
    {
      "index": 34,
      "pos": "Bae_MF_6-1_5083",
      "token_next_uri": "U+002E E.json",
      "token_prev_uri": "chU+002E.json",
      "chN": 164
    },
    {
      "index": 66,
      "pos": "Bae_MF_6-1_5213",
      "token_next_uri": "U+002E U.json",
      "token_prev_uri": "chU+002E.json",
      "chN": 69
    },
    {
      "index": 41,
      "pos": "Bae_MF_6-1_5227",
      "token_next_uri": "U+002E U.json",
      "token_prev_uri": "chU+002E.json",
      "chN": 61
    },
    {
      "index": 46,
      "pos": "Bae_MF_6-1_5625",
      "token_next_uri": "U+002E F.json",
      "token_prev_uri": "chU+002E.json",
      "chN": 49
    },
    {
      "index": 61,
      "pos": "Bae_MF_6-1_5675",
      "token_next_uri": "U+002E A.json",
      "token_prev_uri": "chU+002E.json",
      "chN": 124
    },
    {
      "index": 1,
      "pos_pr": "Bae_MF_6-2_303",
      "pos_nxt": "Bae_MF_6-2_305",
      "token_next_uri": "U+002E D.json",
      "token_prev_uri": "chU+002E.json",
      "chN": 4
    },
    {
      "index": 45,
      "pos": "Bae_MF_6-2_311",
      "token_next_uri": "U+002E E.json",
      "token_prev_uri": "chU+002E.json",
      "chN": 129
    },
    {
      "index": 2,
      "pos": "Bae_MF_6-2_637",
      "token_next_uri": "U+002E  .json",
      "token_prev_uri": "U+002EhU+002E.json",
      "chN": 5
    },
    {
      "index": 32,
      "pos": "Bae_MF_6-2_792",
      "token_next_uri": "U+002E Z.json",
      "token_prev_uri": "chU+002E.json",
      "chN": 80
    },
    {
      "index": 106,
      "pos": "Bae_MF_6-2_1277",
      "token_next_uri": "U+002E N.json",
      "token_prev_uri": "ahU+002E.json",
      "chN": 199
    },
    {
      "index": 1,
      "pos_pr": "Bae_MF_6-2_1921",
      "pos_nxt": "Bae_MF_6-2_1923",
      "token_next_uri": "U+002E M.json",
      "token_prev_uri": "chU+002E.json",
      "chN": 4
    },
    {
      "index": 39,
      "pos": "Bae_MF_6-2_2497",
      "token_next_uri": "U+002E A.json",
      "token_prev_uri": "chU+002E.json",
      "chN": 42
    },
    {
      "index": 7,
      "pos": "Bae_MF_6-2_2974",
      "token_next_uri": "U+002E D.json",
      "token_prev_uri": "chU+002E.json",
      "chN": 10
    },
    {
      "index": 21,
      "pos": "Bae_MF_6-2_3006",
      "token_next_uri": "U+002E S.json",
      "token_prev_uri": "chU+002E.json",
      "chN": 58
    },
    {
      "index": 104,
      "pos": "Bae_MF_6-2_3051",
      "token_next_uri": "U+002E M.json",
      "token_prev_uri": "chU+002E.json",
      "chN": 134
    },
    {
      "index": 20,
      "pos": "Bae_MF_6-2_3257",
      "token_next_uri": "U+002E A.json",
      "token_prev_uri": "chU+002E.json",
      "chN": 23
    },
    {
      "index": 28,
      "pos": "Bae_MF_6-2_3582",
      "token_next_uri": "U+002E A.json",
      "token_prev_uri": "chU+002E.json",
      "chN": 31
    },
    {
      "index": 1,
      "pos_pr": "Bae_MF_6-2_3696",
      "pos_nxt": "Bae_MF_6-2_3698",
      "token_next_uri": "U+002E A.json",
      "token_prev_uri": "chU+002E.json",
      "chN": 4
    },
    {
      "index": 49,
      "pos": "Bae_MF_6-2_3873",
      "token_next_uri": "U+002E a.json",
      "token_prev_uri": "U+002EhU+002E.json",
      "chN": 74
    },
    {
      "index": 38,
      "pos": "Bae_MF_6-2_4810",
      "token_next_uri": "U+002E H.json",
      "token_prev_uri": "chU+002E.json",
      "chN": 265
    },
    {
      "index": 23,
      "pos": "Bae_MF_6-2_5207",
      "token_next_uri": "U+002E L.json",
      "token_prev_uri": "chU+002E.json",
      "chN": 26
    },
    {
      "index": 280,
      "pos": "Bae_MF_6-2_6091",
      "token_next_uri": "U+002E I.json",
      "token_prev_uri": "chU+002E.json",
      "chN": 502
    },
    {
      "index": 45,
      "pos": "Bae_MF_6-2_6226",
      "token_next_uri": "U+002E A.json",
      "token_prev_uri": "chU+002E.json",
      "chN": 703
    },
    {
      "index": 164,
      "pos": "Bae_MF_6-2_6245",
      "token_next_uri": "U+002E I.json",
      "token_prev_uri": "chU+002E.json",
      "chN": 575
    },
    {
      "index": 45,
      "pos": "Bae_MF_6-2_6274",
      "token_next_uri": "U+002E I.json",
      "token_prev_uri": "chU+002E.json",
      "chN": 201
    },
    {
      "index": 78,
      "pos": "Bae_MF_6-2_6292",
      "token_next_uri": "U+002E A.json",
      "token_prev_uri": "chU+002E.json",
      "chN": 320
    },
    {
      "index": 61,
      "pos": "Bae_MF_6-2_6320",
      "token_next_uri": "U+002E A.json",
      "token_prev_uri": "chU+002E.json",
      "chN": 64
    }
  ]
}