{
  "token": "ndo",
  "instances": [
    {
      "index": 36,
      "pos": "Bae_TB_7_5493",
      "token_next_uri": "doU+002E.json",
      "token_prev_uri": "and.json",
      "chN": 41
    },
    {
      "index": 5,
      "pos": "Bae_TB_7_7124",
      "token_next_uri": "dof.json",
      "token_prev_uri": "and.json",
      "chN": 13
    },
    {
      "index": 44,
      "pos": "Bae_TB_7_7152",
      "token_next_uri": "dos.json",
      "token_prev_uri": "and.json",
      "chN": 56
    },
    {
      "index": 5,
      "pos": "Bae_TB_7_7162",
      "token_next_uri": "dos.json",
      "token_prev_uri": "and.json",
      "chN": 15
    },
    {
      "index": 5,
      "pos": "Bae_TB_7_7189",
      "token_next_uri": "dos.json",
      "token_prev_uri": "and.json",
      "chN": 15
    },
    {
      "index": 5,
      "pos": "Bae_TB_7_7219",
      "token_next_uri": "dos.json",
      "token_prev_uri": "and.json",
      "chN": 15
    },
    {
      "index": 5,
      "pos": "Bae_TB_7_7259",
      "token_next_uri": "dos.json",
      "token_prev_uri": "and.json",
      "chN": 15
    },
    {
      "index": 17,
      "pos": "Bae_TB_7_7283",
      "token_next_uri": "dos.json",
      "token_prev_uri": "and.json",
      "chN": 45
    },
    {
      "index": 5,
      "pos": "Bae_TB_7_7309",
      "token_next_uri": "do .json",
      "token_prev_uri": "and.json",
      "chN": 8
    },
    {
      "index": 5,
      "pos": "Bae_TB_7_7376",
      "token_next_uri": "dos.json",
      "token_prev_uri": "and.json",
      "chN": 15
    },
    {
      "index": 5,
      "pos": "Bae_TB_7_7464",
      "token_next_uri": "do .json",
      "token_prev_uri": "and.json",
      "chN": 8
    },
    {
      "index": 5,
      "pos": "Bae_TB_7_7783",
      "token_next_uri": "dos.json",
      "token_prev_uri": "and.json",
      "chN": 15
    },
    {
      "index": 5,
      "pos": "Bae_TB_7_8108",
      "token_next_uri": "dos.json",
      "token_prev_uri": "and.json",
      "chN": 15
    },
    {
      "index": 5,
      "pos": "Bae_TB_7_8733",
      "token_next_uri": "dos.json",
      "token_prev_uri": "and.json",
      "chN": 15
    },
    {
      "index": 5,
      "pos": "Bae_TB_7_8789",
      "token_next_uri": "dos.json",
      "token_prev_uri": "and.json",
      "chN": 15
    },
    {
      "index": 5,
      "pos": "Bae_TB_7_8912",
      "token_next_uri": "dof.json",
      "token_prev_uri": "and.json",
      "chN": 13
    },
    {
      "index": 5,
      "pos": "Bae_TB_7_8948",
      "token_next_uri": "dos.json",
      "token_prev_uri": "and.json",
      "chN": 15
    },
    {
      "index": 5,
      "pos": "Bae_TB_7_11236",
      "token_next_uri": "dos.json",
      "token_prev_uri": "and.json",
      "chN": 15
    },
    {
      "index": 5,
      "pos": "Bae_TB_7_11483",
      "token_next_uri": "dos.json",
      "token_prev_uri": "and.json",
      "chN": 15
    },
    {
      "index": 5,
      "pos": "Bae_TB_7_11678",
      "token_next_uri": "dos.json",
      "token_prev_uri": "and.json",
      "chN": 15
    },
    {
      "index": 5,
      "pos": "Bae_TB_7_13196",
      "token_next_uri": "dos.json",
      "token_prev_uri": "and.json",
      "chN": 15
    },
    {
      "index": 5,
      "pos": "Bae_TB_8_3322",
      "token_next_uri": "dos.json",
      "token_prev_uri": "and.json",
      "chN": 15
    }
  ]
}