{
  "token": "off",
  "instances": [
    {
      "index": 51,
      "pos": "Bae_MF_1_467",
      "token_next_uri": "ffe.json",
      "token_prev_uri": " of.json",
      "chN": 118
    },
    {
      "index": 67,
      "pos": "Bae_MF_1_811",
      "token_next_uri": "ff .json",
      "token_prev_uri": "tof.json",
      "chN": 94
    },
    {
      "index": 143,
      "pos": "Bae_MF_1_1755",
      "token_next_uri": "fft.json",
      "token_prev_uri": "hof.json",
      "chN": 185
    },
    {
      "index": 10,
      "pos": "Bae_MF_1_2521",
      "token_next_uri": "fft.json",
      "token_prev_uri": "hof.json",
      "chN": 335
    },
    {
      "index": 27,
      "pos": "Bae_MF_1_2832",
      "token_next_uri": "ffi.json",
      "token_prev_uri": " of.json",
      "chN": 117
    },
    {
      "index": 101,
      "pos": "Bae_MF_1_3557",
      "token_next_uri": "ffe.json",
      "token_prev_uri": " of.json",
      "chN": 147
    },
    {
      "index": 25,
      "pos": "Bae_MF_1_3596",
      "token_next_uri": "ffe.json",
      "token_prev_uri": " of.json",
      "chN": 49
    },
    {
      "index": 81,
      "pos": "Bae_MF_1_3714",
      "token_next_uri": "ffe.json",
      "token_prev_uri": "tof.json",
      "chN": 144
    },
    {
      "index": 168,
      "pos": "Bae_MF_1_3791",
      "token_next_uri": "ff .json",
      "token_prev_uri": "tof.json",
      "chN": 298
    },
    {
      "index": 9,
      "pos": "Bae_MF_1_3959",
      "token_next_uri": "ffe.json",
      "token_prev_uri": "hof.json",
      "chN": 147
    },
    {
      "index": 99,
      "pos": "Bae_MF_1_4092",
      "token_next_uri": "ffe.json",
      "token_prev_uri": " of.json",
      "chN": 259
    },
    {
      "index": 1,
      "pos": "Bae_MF_1_5159",
      "token_next_uri": "ffe.json",
      "token_prev_uri": " of.json",
      "chN": 209
    },
    {
      "index": 48,
      "pos": "Bae_MF_1_5184",
      "token_next_uri": "ffe.json",
      "token_prev_uri": " of.json",
      "chN": 85
    },
    {
      "index": 395,
      "pos": "Bae_MF_1_5292",
      "token_next_uri": "ffe.json",
      "token_prev_uri": " of.json",
      "chN": 419
    },
    {
      "index": 5,
      "pos": "Bae_MF_1_5511",
      "token_next_uri": "ffn.json",
      "token_prev_uri": "Hof.json",
      "chN": 259
    },
    {
      "index": 59,
      "pos": "Bae_MF_1_5870",
      "token_next_uri": "fft.json",
      "token_prev_uri": "hof.json",
      "chN": 69
    },
    {
      "index": 119,
      "pos": "Bae_MF_1_7251",
      "token_next_uri": "ff,.json",
      "token_prev_uri": "tof.json",
      "chN": 156
    },
    {
      "index": 23,
      "pos": "Bae_MF_1_7898",
      "token_next_uri": "ffi.json",
      "token_prev_uri": " of.json",
      "chN": 55
    },
    {
      "index": 58,
      "pos": "Bae_MF_1_7921",
      "token_next_uri": "ffe.json",
      "token_prev_uri": " of.json",
      "chN": 102
    },
    {
      "index": 61,
      "pos": "Bae_MF_1_7925",
      "token_next_uri": "ffe.json",
      "token_prev_uri": " of.json",
      "chN": 81
    },
    {
      "index": 26,
      "pos": "Bae_MF_1_7953",
      "token_next_uri": "ffe.json",
      "token_prev_uri": " of.json",
      "chN": 185
    },
    {
      "index": 1,
      "pos": "Bae_MF_1_8017",
      "token_next_uri": "ffm.json",
      "token_prev_uri": "Hof.json",
      "chN": 22
    },
    {
      "index": 33,
      "pos": "Bae_MF_1_8025",
      "token_next_uri": "ffe.json",
      "token_prev_uri": " of.json",
      "chN": 60
    },
    {
      "index": 41,
      "pos": "Bae_MF_1_8072",
      "token_next_uri": "fft.json",
      "token_prev_uri": "hof.json",
      "chN": 117
    },
    {
      "index": 38,
      "pos": "Bae_MF_1_8145",
      "token_next_uri": "ffe.json",
      "token_prev_uri": " of.json",
      "chN": 64
    },
    {
      "index": 7,
      "pos": "Bae_MF_1_8237",
      "token_next_uri": "fft.json",
      "token_prev_uri": "hof.json",
      "chN": 43
    },
    {
      "index": 34,
      "pos": "Bae_MF_1_9059",
      "token_next_uri": "ffn.json",
      "token_prev_uri": "Hof.json",
      "chN": 137
    },
    {
      "index": 389,
      "pos": "Bae_MF_1_9166",
      "token_next_uri": "ffe.json",
      "token_prev_uri": " of.json",
      "chN": 523
    },
    {
      "index": 108,
      "pos": "Bae_MF_1_9728",
      "token_next_uri": "ffe.json",
      "token_prev_uri": " of.json",
      "chN": 130
    },
    {
      "index": 57,
      "pos": "Bae_MF_1_9962",
      "token_next_uri": "ffe.json",
      "token_prev_uri": " of.json",
      "chN": 222
    },
    {
      "index": 2,
      "pos": "Bae_MF_1_10072",
      "token_next_uri": "ffe.json",
      "token_prev_uri": " of.json",
      "chN": 26
    },
    {
      "index": 17,
      "pos": "Bae_MF_1_10167",
      "token_next_uri": "ffe.json",
      "token_prev_uri": " of.json",
      "chN": 83
    },
    {
      "index": 9,
      "pos": "Bae_MF_1_10337",
      "token_next_uri": "ffe.json",
      "token_prev_uri": " of.json",
      "chN": 250
    },
    {
      "index": 66,
      "pos": "Bae_MF_2_275",
      "token_next_uri": "ffe.json",
      "token_prev_uri": " of.json",
      "chN": 134
    },
    {
      "index": 24,
      "pos": "Bae_MF_2_566",
      "token_next_uri": "ffn.json",
      "token_prev_uri": "Hof.json",
      "chN": 47
    },
    {
      "index": 69,
      "pos": "Bae_MF_2_647",
      "token_next_uri": "fft.json",
      "token_prev_uri": "hof.json",
      "chN": 98
    },
    {
      "index": 357,
      "pos": "Bae_MF_2_1272",
      "token_next_uri": "ffe.json",
      "token_prev_uri": " of.json",
      "chN": 414
    },
    {
      "index": 12,
      "pos": "Bae_MF_2_1323",
      "token_next_uri": "ffe.json",
      "token_prev_uri": " of.json",
      "chN": 43
    },
    {
      "index": 146,
      "pos": "Bae_MF_2_1577",
      "token_next_uri": "ffe.json",
      "token_prev_uri": " of.json",
      "chN": 234
    },
    {
      "index": 349,
      "pos": "Bae_MF_2_3255",
      "token_next_uri": "ffn.json",
      "token_prev_uri": "Hof.json",
      "chN": 421
    },
    {
      "index": 11,
      "pos": "Bae_MF_2_4448",
      "token_next_uri": "ffe.json",
      "token_prev_uri": " of.json",
      "chN": 83
    },
    {
      "index": 47,
      "pos": "Bae_MF_2_4698",
      "token_next_uri": "ffe.json",
      "token_prev_uri": "hof.json",
      "chN": 64
    },
    {
      "index": 131,
      "pos": "Bae_MF_2_4900",
      "token_next_uri": "ffe.json",
      "token_prev_uri": " of.json",
      "chN": 213
    },
    {
      "index": 131,
      "pos": "Bae_MF_2_5007",
      "token_next_uri": "ffe.json",
      "token_prev_uri": " of.json",
      "chN": 141
    },
    {
      "index": 56,
      "pos": "Bae_MF_2_5172",
      "token_next_uri": "ffe.json",
      "token_prev_uri": " of.json",
      "chN": 110
    },
    {
      "index": 128,
      "pos": "Bae_MF_2_5232",
      "token_next_uri": "ffh.json",
      "token_prev_uri": "rof.json",
      "chN": 160
    },
    {
      "index": 48,
      "pos": "Bae_MF_2_5347",
      "token_next_uri": "ffi.json",
      "token_prev_uri": "eof.json",
      "chN": 66
    },
    {
      "index": 1,
      "pos": "Bae_MF_2_5425",
      "token_next_uri": "ffe.json",
      "token_prev_uri": " of.json",
      "chN": 40
    },
    {
      "index": 34,
      "pos": "Bae_MF_2_5558",
      "token_next_uri": "ffe.json",
      "token_prev_uri": " of.json",
      "chN": 176
    },
    {
      "index": 9,
      "pos": "Bae_MF_2_5863",
      "token_next_uri": "ffi.json",
      "token_prev_uri": "eof.json",
      "chN": 34
    },
    {
      "index": 1,
      "pos": "Bae_MF_2_5871",
      "token_next_uri": "ffi.json",
      "token_prev_uri": " of.json",
      "chN": 60
    },
    {
      "index": 55,
      "pos": "Bae_MF_2_7055",
      "token_next_uri": "ffe.json",
      "token_prev_uri": " of.json",
      "chN": 111
    },
    {
      "index": 87,
      "pos": "Bae_MF_2_7281",
      "token_next_uri": "ffe.json",
      "token_prev_uri": "rof.json",
      "chN": 107
    },
    {
      "index": 206,
      "pos": "Bae_MF_2_7354",
      "token_next_uri": "ffe.json",
      "token_prev_uri": "rof.json",
      "chN": 324
    },
    {
      "index": 88,
      "pos": "Bae_MF_2_7409",
      "token_next_uri": "ffn.json",
      "token_prev_uri": "Hof.json",
      "chN": 122
    },
    {
      "index": 45,
      "pos": "Bae_MF_2_7617",
      "token_next_uri": "ffe.json",
      "token_prev_uri": "rof.json",
      "chN": 389
    },
    {
      "index": 180,
      "pos": "Bae_MF_2_7624",
      "token_next_uri": "ffe.json",
      "token_prev_uri": " of.json",
      "chN": 534
    },
    {
      "index": 218,
      "pos": "Bae_MF_2_7624",
      "token_next_uri": "ffe.json",
      "token_prev_uri": "rof.json",
      "chN": 534
    },
    {
      "index": 28,
      "pos": "Bae_MF_2_8680",
      "token_next_uri": "ffe.json",
      "token_prev_uri": " of.json",
      "chN": 52
    },
    {
      "index": 99,
      "pos": "Bae_MF_2_9080",
      "token_next_uri": "ffe.json",
      "token_prev_uri": " of.json",
      "chN": 354
    },
    {
      "index": 8,
      "pos": "Bae_MF_2_9330",
      "token_next_uri": "ff .json",
      "token_prev_uri": "kof.json",
      "chN": 11
    },
    {
      "index": 30,
      "pos": "Bae_MF_2_9492",
      "token_next_uri": "ffe.json",
      "token_prev_uri": " of.json",
      "chN": 41
    },
    {
      "index": 9,
      "pos": "Bae_MF_2_10525",
      "token_next_uri": "ffe.json",
      "token_prev_uri": " of.json",
      "chN": 22
    },
    {
      "index": 88,
      "pos": "Bae_MF_2_10904",
      "token_next_uri": "ffi.json",
      "token_prev_uri": " of.json",
      "chN": 275
    },
    {
      "index": 41,
      "pos": "Bae_MF_2_11733",
      "token_next_uri": "ffn.json",
      "token_prev_uri": "hof.json",
      "chN": 114
    },
    {
      "index": 43,
      "pos": "Bae_MF_2_12053",
      "token_next_uri": "ffe.json",
      "token_prev_uri": " of.json",
      "chN": 70
    },
    {
      "index": 17,
      "pos": "Bae_TB_1_955",
      "token_next_uri": "ffe.json",
      "token_prev_uri": " of.json",
      "chN": 84
    },
    {
      "index": 909,
      "pos": "Bae_TB_1_1414",
      "token_next_uri": "ffe.json",
      "token_prev_uri": " of.json",
      "chN": 1315
    },
    {
      "index": 15,
      "pos": "Bae_TB_1_1447",
      "token_next_uri": "fft.json",
      "token_prev_uri": "hof.json",
      "chN": 265
    },
    {
      "index": 70,
      "pos": "Bae_TB_1_1526",
      "token_next_uri": "ffn.json",
      "token_prev_uri": "Hof.json",
      "chN": 415
    },
    {
      "index": 68,
      "pos": "Bae_TB_1_1604",
      "token_next_uri": "ff .json",
      "token_prev_uri": "tof.json",
      "chN": 95
    },
    {
      "index": 73,
      "pos": "Bae_TB_1_2943",
      "token_next_uri": "ffe.json",
      "token_prev_uri": " of.json",
      "chN": 378
    },
    {
      "index": 136,
      "pos": "Bae_TB_1_3385",
      "token_next_uri": "fft.json",
      "token_prev_uri": "hof.json",
      "chN": 178
    },
    {
      "index": 6,
      "pos": "Bae_TB_1_5360",
      "token_next_uri": "fft.json",
      "token_prev_uri": "hof.json",
      "chN": 55
    },
    {
      "index": 27,
      "pos": "Bae_TB_1_6031",
      "token_next_uri": "ffi.json",
      "token_prev_uri": " of.json",
      "chN": 118
    },
    {
      "index": 31,
      "pos": "Bae_TB_1_6573",
      "token_next_uri": "ffe.json",
      "token_prev_uri": " of.json",
      "chN": 223
    },
    {
      "index": 101,
      "pos": "Bae_TB_1_7184",
      "token_next_uri": "ffe.json",
      "token_prev_uri": " of.json",
      "chN": 147
    },
    {
      "index": 1,
      "pos": "Bae_TB_1_7240",
      "token_next_uri": "ffe.json",
      "token_prev_uri": " of.json",
      "chN": 25
    },
    {
      "index": 62,
      "pos": "Bae_TB_1_7425",
      "token_next_uri": "ffe.json",
      "token_prev_uri": "tof.json",
      "chN": 68
    },
    {
      "index": 21,
      "pos": "Bae_TB_1_7569",
      "token_next_uri": "ff .json",
      "token_prev_uri": "tof.json",
      "chN": 151
    },
    {
      "index": 1617,
      "pos": "Bae_TB_1_8283",
      "token_next_uri": "ffe.json",
      "token_prev_uri": " of.json",
      "chN": 2403
    },
    {
      "index": 63,
      "pos": "Bae_TB_1_9955",
      "token_next_uri": "ffn.json",
      "token_prev_uri": "Hof.json",
      "chN": 138
    },
    {
      "index": 79,
      "pos": "Bae_TB_1_10036",
      "token_next_uri": "ffe.json",
      "token_prev_uri": " of.json",
      "chN": 101
    },
    {
      "index": 65,
      "pos": "Bae_TB_1_10237",
      "token_next_uri": "ffn.json",
      "token_prev_uri": "Hof.json",
      "chN": 227
    },
    {
      "index": 305,
      "pos": "Bae_TB_1_10299",
      "token_next_uri": "ffe.json",
      "token_prev_uri": "hof.json",
      "chN": 625
    },
    {
      "index": 51,
      "pos": "Bae_TB_1_10342",
      "token_next_uri": "fft.json",
      "token_prev_uri": "hof.json",
      "chN": 104
    },
    {
      "index": 190,
      "pos": "Bae_TB_1_10383",
      "token_next_uri": "ffn.json",
      "token_prev_uri": "Hof.json",
      "chN": 535
    },
    {
      "index": 1,
      "pos": "Bae_TB_1_10900",
      "token_next_uri": "ffe.json",
      "token_prev_uri": " of.json",
      "chN": 53
    },
    {
      "index": 1,
      "pos": "Bae_TB_1_10982",
      "token_next_uri": "ffe.json",
      "token_prev_uri": " of.json",
      "chN": 68
    },
    {
      "index": 55,
      "pos": "Bae_TB_1_11180",
      "token_next_uri": "ffe.json",
      "token_prev_uri": " of.json",
      "chN": 79
    },
    {
      "index": 5,
      "pos": "Bae_TB_1_11652",
      "token_next_uri": "ffn.json",
      "token_prev_uri": "Hof.json",
      "chN": 260
    },
    {
      "index": 322,
      "pos": "Bae_TB_1_11951",
      "token_next_uri": "ffe.json",
      "token_prev_uri": " of.json",
      "chN": 425
    },
    {
      "index": 59,
      "pos": "Bae_TB_1_12515",
      "token_next_uri": "fft.json",
      "token_prev_uri": "hof.json",
      "chN": 69
    },
    {
      "index": 20,
      "pos": "Bae_TB_1_13730",
      "token_next_uri": "ff,.json",
      "token_prev_uri": "hof.json",
      "chN": 23
    },
    {
      "index": 213,
      "pos": "Bae_TB_1_13931",
      "token_next_uri": "ffe.json",
      "token_prev_uri": " of.json",
      "chN": 615
    },
    {
      "index": 15,
      "pos": "Bae_TB_1_14183",
      "token_next_uri": "ffn.json",
      "token_prev_uri": "hof.json",
      "chN": 258
    },
    {
      "index": 42,
      "pos": "Bae_TB_1_14427",
      "token_next_uri": "ffe.json",
      "token_prev_uri": " of.json",
      "chN": 428
    },
    {
      "index": 92,
      "pos": "Bae_TB_1_14460",
      "token_next_uri": "ffe.json",
      "token_prev_uri": " of.json",
      "chN": 235
    },
    {
      "index": 98,
      "pos": "Bae_TB_1_14621",
      "token_next_uri": "ffe.json",
      "token_prev_uri": " of.json",
      "chN": 144
    },
    {
      "index": 13,
      "pos": "Bae_TB_1_14729",
      "token_next_uri": "ffe.json",
      "token_prev_uri": "hof.json",
      "chN": 58
    },
    {
      "index": 115,
      "pos": "Bae_TB_2_268",
      "token_next_uri": "ff,.json",
      "token_prev_uri": "tof.json",
      "chN": 152
    },
    {
      "index": 210,
      "pos": "Bae_TB_2_648",
      "token_next_uri": "ffe.json",
      "token_prev_uri": " of.json",
      "chN": 242
    },
    {
      "index": 23,
      "pos": "Bae_TB_2_1591",
      "token_next_uri": "ffi.json",
      "token_prev_uri": " of.json",
      "chN": 55
    },
    {
      "index": 54,
      "pos": "Bae_TB_2_1630",
      "token_next_uri": "ffe.json",
      "token_prev_uri": " of.json",
      "chN": 98
    },
    {
      "index": 14,
      "pos": "Bae_TB_2_1643",
      "token_next_uri": "ffe.json",
      "token_prev_uri": " of.json",
      "chN": 34
    },
    {
      "index": 26,
      "pos": "Bae_TB_2_1672",
      "token_next_uri": "ffe.json",
      "token_prev_uri": " of.json",
      "chN": 79
    },
    {
      "index": 1,
      "pos": "Bae_TB_2_1754",
      "token_next_uri": "ffm.json",
      "token_prev_uri": "Hof.json",
      "chN": 22
    },
    {
      "index": 116,
      "pos": "Bae_TB_2_1760",
      "token_next_uri": "ffe.json",
      "token_prev_uri": " of.json",
      "chN": 136
    },
    {
      "index": 16,
      "pos": "Bae_TB_2_1884",
      "token_next_uri": "fft.json",
      "token_prev_uri": "hof.json",
      "chN": 91
    },
    {
      "index": 38,
      "pos": "Bae_TB_2_2054",
      "token_next_uri": "ffe.json",
      "token_prev_uri": " of.json",
      "chN": 78
    },
    {
      "index": 7,
      "pos": "Bae_TB_2_2147",
      "token_next_uri": "fft.json",
      "token_prev_uri": "hof.json",
      "chN": 43
    },
    {
      "index": 109,
      "pos": "Bae_TB_2_3480",
      "token_next_uri": "ffe.json",
      "token_prev_uri": "rof.json",
      "chN": 136
    },
    {
      "index": 100,
      "pos": "Bae_TB_2_3878",
      "token_next_uri": "ffn.json",
      "token_prev_uri": "Hof.json",
      "chN": 244
    },
    {
      "index": 21,
      "pos": "Bae_TB_2_4119",
      "token_next_uri": "ffe.json",
      "token_prev_uri": " of.json",
      "chN": 157
    },
    {
      "index": 58,
      "pos": "Bae_TB_2_4321",
      "token_next_uri": "ffi.json",
      "token_prev_uri": " of.json",
      "chN": 315
    },
    {
      "index": 34,
      "pos": "Bae_TB_2_5020",
      "token_next_uri": "ffn.json",
      "token_prev_uri": "Hof.json",
      "chN": 61
    },
    {
      "index": 46,
      "pos": "Bae_TB_2_5649",
      "token_next_uri": "ffe.json",
      "token_prev_uri": " of.json",
      "chN": 64
    },
    {
      "index": 97,
      "pos": "Bae_TB_2_5868",
      "token_next_uri": "ffe.json",
      "token_prev_uri": " of.json",
      "chN": 186
    },
    {
      "index": 117,
      "pos": "Bae_TB_2_5868",
      "token_next_uri": "ff .json",
      "token_prev_uri": "tof.json",
      "chN": 186
    },
    {
      "index": 86,
      "pos": "Bae_TB_2_6654",
      "token_next_uri": "ffe.json",
      "token_prev_uri": " of.json",
      "chN": 104
    },
    {
      "index": 103,
      "pos": "Bae_TB_2_6929",
      "token_next_uri": "ffe.json",
      "token_prev_uri": " of.json",
      "chN": 173
    },
    {
      "index": 30,
      "pos": "Bae_TB_2_7046",
      "token_next_uri": "ffe.json",
      "token_prev_uri": " of.json",
      "chN": 198
    },
    {
      "index": 58,
      "pos": "Bae_TB_2_7258",
      "token_next_uri": "ffe.json",
      "token_prev_uri": " of.json",
      "chN": 224
    },
    {
      "index": 2,
      "pos": "Bae_TB_2_7465",
      "token_next_uri": "ffe.json",
      "token_prev_uri": " of.json",
      "chN": 26
    },
    {
      "index": 259,
      "pos": "Bae_TB_2_7560",
      "token_next_uri": "ffe.json",
      "token_prev_uri": " of.json",
      "chN": 331
    },
    {
      "index": 9,
      "pos": "Bae_TB_2_7807",
      "token_next_uri": "ffe.json",
      "token_prev_uri": " of.json",
      "chN": 157
    },
    {
      "index": 31,
      "pos": "Bae_TB_2_8280",
      "token_next_uri": "ffe.json",
      "token_prev_uri": " of.json",
      "chN": 106
    },
    {
      "index": 1,
      "pos": "Bae_TB_2_9241",
      "token_next_uri": "ffm.json",
      "token_prev_uri": "Hof.json",
      "chN": 22
    },
    {
      "index": 9,
      "pos": "Bae_TB_2_9292",
      "token_next_uri": "ffi.json",
      "token_prev_uri": " of.json",
      "chN": 48
    },
    {
      "index": 66,
      "pos": "Bae_TB_2_10204",
      "token_next_uri": "ffe.json",
      "token_prev_uri": " of.json",
      "chN": 134
    },
    {
      "index": 24,
      "pos": "Bae_TB_2_10657",
      "token_next_uri": "ffn.json",
      "token_prev_uri": "Hof.json",
      "chN": 47
    },
    {
      "index": 1,
      "pos": "Bae_TB_2_10787",
      "token_next_uri": "fft.json",
      "token_prev_uri": "hof.json",
      "chN": 7
    },
    {
      "index": 22,
      "pos": "Bae_TB_2_11682",
      "token_next_uri": "ffe.json",
      "token_prev_uri": " of.json",
      "chN": 71
    },
    {
      "index": 12,
      "pos": "Bae_TB_2_11800",
      "token_next_uri": "ffe.json",
      "token_prev_uri": " of.json",
      "chN": 135
    },
    {
      "index": 176,
      "pos": "Bae_TB_2_12284",
      "token_next_uri": "ffe.json",
      "token_prev_uri": " of.json",
      "chN": 264
    },
    {
      "index": 198,
      "pos": "Bae_TB_2_12525",
      "token_next_uri": "ffe.json",
      "token_prev_uri": "hof.json",
      "chN": 216
    },
    {
      "index": 39,
      "pos": "Bae_TB_2_12553",
      "token_next_uri": "ffe.json",
      "token_prev_uri": "tof.json",
      "chN": 445
    },
    {
      "index": 751,
      "pos": "Bae_TB_2_12640",
      "token_next_uri": "ffe.json",
      "token_prev_uri": "rof.json",
      "chN": 811
    },
    {
      "index": 24,
      "pos": "Bae_TB_2_12809",
      "token_next_uri": "ffe.json",
      "token_prev_uri": "hof.json",
      "chN": 299
    },
    {
      "index": 21,
      "pos": "Bae_TB_2_13694",
      "token_next_uri": "ffn.json",
      "token_prev_uri": "Hof.json",
      "chN": 48
    },
    {
      "index": 57,
      "pos": "Bae_TB_2_13835",
      "token_next_uri": "ffe.json",
      "token_prev_uri": " of.json",
      "chN": 841
    },
    {
      "index": 317,
      "pos": "Bae_TB_2_13835",
      "token_next_uri": "ffe.json",
      "token_prev_uri": " of.json",
      "chN": 841
    },
    {
      "index": 5,
      "pos": "Bae_TB_2_13838",
      "token_next_uri": "ffe.json",
      "token_prev_uri": "hof.json",
      "chN": 222
    },
    {
      "index": 217,
      "pos": "Bae_TB_2_16344",
      "token_next_uri": "ffn.json",
      "token_prev_uri": "Hof.json",
      "chN": 288
    },
    {
      "index": 208,
      "pos": "Bae_TB_3_574",
      "token_next_uri": "ffe.json",
      "token_prev_uri": "Hof.json",
      "chN": 296
    },
    {
      "index": 11,
      "pos": "Bae_TB_3_1880",
      "token_next_uri": "ffe.json",
      "token_prev_uri": " of.json",
      "chN": 235
    },
    {
      "index": 8,
      "pos": "Bae_TB_3_2288",
      "token_next_uri": "ffe.json",
      "token_prev_uri": "hof.json",
      "chN": 25
    },
    {
      "index": 57,
      "pos": "Bae_TB_3_2596",
      "token_next_uri": "ffe.json",
      "token_prev_uri": " of.json",
      "chN": 139
    },
    {
      "index": 96,
      "pos": "Bae_TB_3_2756",
      "token_next_uri": "ffe.json",
      "token_prev_uri": " of.json",
      "chN": 106
    },
    {
      "index": 13,
      "pos": "Bae_TB_3_2986",
      "token_next_uri": "ffe.json",
      "token_prev_uri": " of.json",
      "chN": 67
    },
    {
      "index": 18,
      "pos": "Bae_TB_3_3081",
      "token_next_uri": "ffh.json",
      "token_prev_uri": "rof.json",
      "chN": 49
    },
    {
      "index": 65,
      "pos": "Bae_TB_3_3219",
      "token_next_uri": "ffi.json",
      "token_prev_uri": "eof.json",
      "chN": 83
    },
    {
      "index": 1,
      "pos": "Bae_TB_3_3315",
      "token_next_uri": "ffe.json",
      "token_prev_uri": " of.json",
      "chN": 40
    },
    {
      "index": 34,
      "pos": "Bae_TB_3_3456",
      "token_next_uri": "ffe.json",
      "token_prev_uri": " of.json",
      "chN": 67
    },
    {
      "index": 9,
      "pos": "Bae_TB_3_3949",
      "token_next_uri": "ffi.json",
      "token_prev_uri": "eof.json",
      "chN": 34
    },
    {
      "index": 1,
      "pos": "Bae_TB_3_3957",
      "token_next_uri": "ffi.json",
      "token_prev_uri": " of.json",
      "chN": 59
    },
    {
      "index": 8,
      "pos": "Bae_TB_3_4233",
      "token_next_uri": "ffe.json",
      "token_prev_uri": "rof.json",
      "chN": 71
    },
    {
      "index": 74,
      "pos": "Bae_TB_3_4245",
      "token_next_uri": "ffi.json",
      "token_prev_uri": " of.json",
      "chN": 100
    },
    {
      "index": 142,
      "pos": "Bae_TB_3_4412",
      "token_next_uri": "ffe.json",
      "token_prev_uri": " of.json",
      "chN": 290
    },
    {
      "index": 478,
      "pos": "Bae_TB_3_5394",
      "token_next_uri": "ffe.json",
      "token_prev_uri": "hof.json",
      "chN": 620
    },
    {
      "index": 55,
      "pos": "Bae_TB_3_6148",
      "token_next_uri": "ffe.json",
      "token_prev_uri": " of.json",
      "chN": 111
    },
    {
      "index": 0,
      "pos": "Bae_TB_3_6285",
      "token_next_uri": "ffi.json",
      "token_prev_uri": " of.json",
      "chN": 19
    },
    {
      "index": 84,
      "pos": "Bae_TB_3_6731",
      "token_next_uri": "ffe.json",
      "token_prev_uri": "rof.json",
      "chN": 104
    },
    {
      "index": 86,
      "pos": "Bae_TB_3_6906",
      "token_next_uri": "ffe.json",
      "token_prev_uri": "rof.json",
      "chN": 177
    },
    {
      "index": 88,
      "pos": "Bae_TB_3_6984",
      "token_next_uri": "ffn.json",
      "token_prev_uri": "Hof.json",
      "chN": 122
    },
    {
      "index": 152,
      "pos": "Bae_TB_3_7294",
      "token_next_uri": "ffe.json",
      "token_prev_uri": "rof.json",
      "chN": 652
    },
    {
      "index": 24,
      "pos": "Bae_TB_3_7296",
      "token_next_uri": "ffe.json",
      "token_prev_uri": " of.json",
      "chN": 379
    },
    {
      "index": 62,
      "pos": "Bae_TB_3_7296",
      "token_next_uri": "ffe.json",
      "token_prev_uri": "rof.json",
      "chN": 379
    },
    {
      "index": 5,
      "pos": "Bae_TB_3_8151",
      "token_next_uri": "ffi.json",
      "token_prev_uri": " of.json",
      "chN": 26
    },
    {
      "index": 10,
      "pos": "Bae_TB_3_8162",
      "token_next_uri": "ffi.json",
      "token_prev_uri": " of.json",
      "chN": 202
    },
    {
      "index": 24,
      "pos": "Bae_TB_3_9057",
      "token_next_uri": "ffe.json",
      "token_prev_uri": " of.json",
      "chN": 48
    },
    {
      "index": 39,
      "pos": "Bae_TB_3_9336",
      "token_next_uri": "fft.json",
      "token_prev_uri": "hof.json",
      "chN": 127
    },
    {
      "index": 36,
      "pos": "Bae_TB_3_9910",
      "token_next_uri": "ffe.json",
      "token_prev_uri": " of.json",
      "chN": 155
    },
    {
      "index": 8,
      "pos": "Bae_TB_3_10262",
      "token_next_uri": "ff .json",
      "token_prev_uri": "kof.json",
      "chN": 11
    },
    {
      "index": 11,
      "pos": "Bae_TB_3_10431",
      "token_next_uri": "ffe.json",
      "token_prev_uri": " of.json",
      "chN": 22
    },
    {
      "index": 4,
      "pos": "Bae_TB_3_12789",
      "token_next_uri": "ffi.json",
      "token_prev_uri": " of.json",
      "chN": 191
    },
    {
      "index": 3,
      "pos": "Bae_TB_3_13098",
      "token_next_uri": "ffe.json",
      "token_prev_uri": "tof.json",
      "chN": 136
    },
    {
      "index": 41,
      "pos": "Bae_TB_3_14364",
      "token_next_uri": "ffn.json",
      "token_prev_uri": "hof.json",
      "chN": 78
    },
    {
      "index": 43,
      "pos": "Bae_TB_3_14973",
      "token_next_uri": "ffe.json",
      "token_prev_uri": " of.json",
      "chN": 70
    }
  ]
}