{
  "token": "urs",
  "instances": [
    {
      "index": 23,
      "pos": "Bae_MF_6-1_5129",
      "chN": 121,
      "token_next_uri": "rsa.json",
      "token_prev_uri": "rur.json"
    },
    {
      "index": 5,
      "pos": "Bae_MF_6-2_832",
      "chN": 14,
      "token_next_uri": "rst.json",
      "token_prev_uri": "wur.json"
    },
    {
      "index": 162,
      "pos": "Bae_MF_6-2_6235",
      "chN": 291,
      "token_next_uri": "rsa.json",
      "token_prev_uri": "rur.json"
    },
    {
      "index": 283,
      "pos": "Bae_TB_7_1059",
      "chN": 444,
      "token_next_uri": "rsp.json",
      "token_prev_uri": " ur.json"
    },
    {
      "index": 117,
      "pos": "Bae_TB_7_2121",
      "chN": 305,
      "token_next_uri": "rse.json",
      "token_prev_uri": "Kur.json"
    },
    {
      "index": 76,
      "pos": "Bae_TB_7_2127",
      "chN": 260,
      "token_next_uri": "rse.json",
      "token_prev_uri": "Kur.json"
    },
    {
      "index": 144,
      "pos": "Bae_TB_7_2144",
      "chN": 192,
      "token_next_uri": "rse.json",
      "token_prev_uri": "kur.json"
    },
    {
      "index": 64,
      "pos": "Bae_TB_7_2152",
      "chN": 379,
      "token_next_uri": "rse.json",
      "token_prev_uri": "kur.json"
    },
    {
      "index": 202,
      "pos": "Bae_TB_7_2185",
      "chN": 262,
      "token_next_uri": "rse.json",
      "token_prev_uri": "kur.json"
    },
    {
      "index": 188,
      "pos": "Bae_TB_7_2199",
      "chN": 196,
      "token_next_uri": "rse.json",
      "token_prev_uri": "Kur.json"
    },
    {
      "index": 77,
      "pos": "Bae_TB_7_2219",
      "chN": 102,
      "token_next_uri": "rse.json",
      "token_prev_uri": "Kur.json"
    },
    {
      "index": 22,
      "pos": "Bae_TB_7_2269",
      "chN": 396,
      "token_next_uri": "rse.json",
      "token_prev_uri": "kur.json"
    },
    {
      "index": 144,
      "pos": "Bae_TB_7_2269",
      "chN": 396,
      "token_next_uri": "rse.json",
      "token_prev_uri": "Kur.json"
    },
    {
      "index": 33,
      "pos": "Bae_TB_7_2277",
      "chN": 207,
      "token_next_uri": "rse.json",
      "token_prev_uri": "Kur.json"
    },
    {
      "index": 346,
      "pos": "Bae_TB_7_2318",
      "chN": 503,
      "token_next_uri": "rse.json",
      "token_prev_uri": "kur.json"
    },
    {
      "index": 69,
      "pos": "Bae_TB_7_2374",
      "chN": 115,
      "token_next_uri": "rse.json",
      "token_prev_uri": "Kur.json"
    },
    {
      "index": 385,
      "pos": "Bae_TB_7_2440",
      "chN": 669,
      "token_next_uri": "rse.json",
      "token_prev_uri": "kur.json"
    },
    {
      "index": 26,
      "pos": "Bae_TB_7_2461",
      "chN": 114,
      "token_next_uri": "rse.json",
      "token_prev_uri": "kur.json"
    },
    {
      "index": 37,
      "pos": "Bae_TB_7_2482",
      "chN": 145,
      "token_next_uri": "rse.json",
      "token_prev_uri": "kur.json"
    },
    {
      "index": 24,
      "pos": "Bae_TB_7_11250",
      "chN": 33,
      "token_next_uri": "rsa.json",
      "token_prev_uri": "rur.json"
    },
    {
      "index": 6,
      "pos": "Bae_TB_8_3285",
      "chN": 16,
      "token_next_uri": "rst.json",
      "token_prev_uri": "wur.json"
    }
  ]
}