{
  "token": "g u",
  "instances": [
    {
      "index": 15,
      "pos": "Bae_MF_6-1_208",
      "token_next_uri": " un.json",
      "token_prev_uri": "ng .json",
      "chN": 63
    },
    {
      "index": 94,
      "pos": "Bae_MF_6-1_451",
      "token_next_uri": " un.json",
      "token_prev_uri": "ng .json",
      "chN": 190
    },
    {
      "index": 82,
      "pos": "Bae_MF_6-1_582",
      "token_next_uri": " us.json",
      "token_prev_uri": "ng .json",
      "chN": 106
    },
    {
      "index": 94,
      "pos": "Bae_MF_6-1_611",
      "token_next_uri": " um.json",
      "token_prev_uri": "ag .json",
      "chN": 170
    },
    {
      "index": 111,
      "pos": "Bae_MF_6-1_1191",
      "token_next_uri": " un.json",
      "token_prev_uri": "ig .json",
      "chN": 136
    },
    {
      "index": 201,
      "pos": "Bae_MF_6-1_1332",
      "token_next_uri": " un.json",
      "token_prev_uri": "ig .json",
      "chN": 250
    },
    {
      "index": 57,
      "pos": "Bae_MF_6-1_1396",
      "token_next_uri": " un.json",
      "token_prev_uri": "ng .json",
      "chN": 1165
    },
    {
      "index": 293,
      "pos": "Bae_MF_6-1_1396",
      "token_next_uri": " un.json",
      "token_prev_uri": "ng .json",
      "chN": 1165
    },
    {
      "index": 435,
      "pos": "Bae_MF_6-1_1396",
      "token_next_uri": " un.json",
      "token_prev_uri": "ng .json",
      "chN": 1165
    },
    {
      "index": 336,
      "pos": "Bae_MF_6-1_1730",
      "token_next_uri": " un.json",
      "token_prev_uri": "ig .json",
      "chN": 433
    },
    {
      "index": 53,
      "pos": "Bae_MF_6-1_1931",
      "token_next_uri": " un.json",
      "token_prev_uri": "ng .json",
      "chN": 110
    },
    {
      "index": 37,
      "pos": "Bae_MF_6-1_2015",
      "token_next_uri": " un.json",
      "token_prev_uri": "ng .json",
      "chN": 393
    },
    {
      "index": 50,
      "pos": "Bae_MF_6-1_2157",
      "token_next_uri": " un.json",
      "token_prev_uri": "ng .json",
      "chN": 151
    },
    {
      "index": 0,
      "pos_pr": "Bae_MF_6-1_3037",
      "pos_nxt": "Bae_MF_6-1_3044",
      "token_next_uri": " un.json",
      "token_prev_uri": "ng .json",
      "chN": 4
    },
    {
      "index": 83,
      "pos": "Bae_MF_6-1_3996",
      "token_next_uri": " un.json",
      "token_prev_uri": "ng .json",
      "chN": 121
    },
    {
      "index": 9,
      "pos": "Bae_MF_6-1_4279",
      "token_next_uri": " un.json",
      "token_prev_uri": "ig .json",
      "chN": 31
    },
    {
      "index": 72,
      "pos": "Bae_MF_6-1_4396",
      "token_next_uri": " un.json",
      "token_prev_uri": "ng .json",
      "chN": 565
    },
    {
      "index": 67,
      "pos": "Bae_MF_6-1_4503",
      "token_next_uri": " un.json",
      "token_prev_uri": "ng .json",
      "chN": 95
    },
    {
      "index": 58,
      "pos": "Bae_MF_6-1_4546",
      "token_next_uri": " un.json",
      "token_prev_uri": "ng .json",
      "chN": 277
    },
    {
      "index": 0,
      "pos_pr": "Bae_MF_6-1_4682",
      "pos_nxt": "Bae_MF_6-1_4690",
      "token_next_uri": " un.json",
      "token_prev_uri": "ng .json",
      "chN": 4
    },
    {
      "index": 73,
      "pos": "Bae_MF_6-2_268",
      "token_next_uri": " un.json",
      "token_prev_uri": "ig .json",
      "chN": 156
    },
    {
      "index": 330,
      "pos": "Bae_MF_6-2_905",
      "token_next_uri": " un.json",
      "token_prev_uri": "ng .json",
      "chN": 420
    },
    {
      "index": 80,
      "pos": "Bae_MF_6-2_953",
      "token_next_uri": " un.json",
      "token_prev_uri": "ng .json",
      "chN": 145
    },
    {
      "index": 119,
      "pos": "Bae_MF_6-2_995",
      "token_next_uri": " un.json",
      "token_prev_uri": "ng .json",
      "chN": 367
    },
    {
      "index": 1,
      "pos_pr": "Bae_MF_6-2_1232",
      "pos_nxt": "Bae_MF_6-2_1234",
      "token_next_uri": " un.json",
      "token_prev_uri": "gg .json",
      "chN": 4
    },
    {
      "index": 18,
      "pos": "Bae_MF_6-2_1504",
      "token_next_uri": " un.json",
      "token_prev_uri": "ng .json",
      "chN": 36
    },
    {
      "index": 23,
      "pos": "Bae_MF_6-2_1514",
      "token_next_uri": " un.json",
      "token_prev_uri": "ig .json",
      "chN": 57
    },
    {
      "index": 97,
      "pos": "Bae_MF_6-2_1744",
      "token_next_uri": " un.json",
      "token_prev_uri": "ng .json",
      "chN": 117
    },
    {
      "index": 1,
      "pos_pr": "Bae_MF_6-2_1746",
      "pos_nxt": "Bae_MF_6-2_1748",
      "token_next_uri": " un.json",
      "token_prev_uri": "ag .json",
      "chN": 4
    },
    {
      "index": 56,
      "pos": "Bae_MF_6-2_1835",
      "token_next_uri": " un.json",
      "token_prev_uri": "ng .json",
      "chN": 131
    },
    {
      "index": 183,
      "pos": "Bae_MF_6-2_1905",
      "token_next_uri": " un.json",
      "token_prev_uri": "ng .json",
      "chN": 543
    },
    {
      "index": 317,
      "pos": "Bae_MF_6-2_1905",
      "token_next_uri": " un.json",
      "token_prev_uri": "ng .json",
      "chN": 543
    },
    {
      "index": 112,
      "pos": "Bae_MF_6-2_1933",
      "token_next_uri": " un.json",
      "token_prev_uri": "ng .json",
      "chN": 118
    },
    {
      "index": 15,
      "pos": "Bae_MF_6-2_2211",
      "token_next_uri": " un.json",
      "token_prev_uri": "ng .json",
      "chN": 114
    },
    {
      "index": 30,
      "pos": "Bae_MF_6-2_2211",
      "token_next_uri": " un.json",
      "token_prev_uri": "ng .json",
      "chN": 114
    },
    {
      "index": 45,
      "pos": "Bae_MF_6-2_3148",
      "token_next_uri": " un.json",
      "token_prev_uri": "ng .json",
      "chN": 100
    },
    {
      "index": 54,
      "pos": "Bae_MF_6-2_3370",
      "token_next_uri": " un.json",
      "token_prev_uri": "ng .json",
      "chN": 133
    },
    {
      "index": 24,
      "pos": "Bae_MF_6-2_3527",
      "token_next_uri": " un.json",
      "token_prev_uri": "ng .json",
      "chN": 174
    },
    {
      "index": 1,
      "pos_pr": "Bae_MF_6-2_3614",
      "pos_nxt": "Bae_MF_6-2_3616",
      "token_next_uri": " un.json",
      "token_prev_uri": "rg .json",
      "chN": 4
    },
    {
      "index": 119,
      "pos": "Bae_MF_6-2_4898",
      "token_next_uri": " un.json",
      "token_prev_uri": "ng .json",
      "chN": 213
    },
    {
      "index": 12,
      "pos": "Bae_MF_6-2_5414",
      "token_next_uri": " un.json",
      "token_prev_uri": "ng .json",
      "chN": 201
    },
    {
      "index": 341,
      "pos": "Bae_MF_6-2_5517",
      "token_next_uri": " un.json",
      "token_prev_uri": "ng .json",
      "chN": 678
    },
    {
      "index": 668,
      "pos": "Bae_MF_6-2_5517",
      "token_next_uri": " un.json",
      "token_prev_uri": "ng .json",
      "chN": 678
    },
    {
      "index": 130,
      "pos": "Bae_MF_6-2_5615",
      "token_next_uri": " un.json",
      "token_prev_uri": "ng .json",
      "chN": 217
    },
    {
      "index": 135,
      "pos": "Bae_MF_6-2_5741",
      "token_next_uri": " un.json",
      "token_prev_uri": "ag .json",
      "chN": 195
    },
    {
      "index": 1,
      "pos_pr": "Bae_MF_6-2_5803",
      "pos_nxt": "Bae_MF_6-2_5805",
      "token_next_uri": " un.json",
      "token_prev_uri": "rg .json",
      "chN": 4
    },
    {
      "index": 1,
      "pos_pr": "Bae_MF_6-2_6216",
      "pos_nxt": "Bae_MF_6-2_6218",
      "token_next_uri": " un.json",
      "token_prev_uri": "rg .json",
      "chN": 4
    },
    {
      "index": 157,
      "pos": "Bae_MF_6-2_6342",
      "token_next_uri": " un.json",
      "token_prev_uri": "ig .json",
      "chN": 562
    },
    {
      "index": 263,
      "pos": "Bae_MF_6-2_6350",
      "token_next_uri": " un.json",
      "token_prev_uri": "ig .json",
      "chN": 329
    },
    {
      "index": 13,
      "pos": "Bae_TB_7_225",
      "token_next_uri": " un.json",
      "token_prev_uri": "ng .json",
      "chN": 84
    },
    {
      "index": 88,
      "pos": "Bae_TB_7_344",
      "token_next_uri": " un.json",
      "token_prev_uri": "ng .json",
      "chN": 118
    },
    {
      "index": 26,
      "pos": "Bae_TB_7_851",
      "token_next_uri": " un.json",
      "token_prev_uri": "ng .json",
      "chN": 63
    },
    {
      "index": 45,
      "pos": "Bae_TB_7_868",
      "token_next_uri": " un.json",
      "token_prev_uri": "ng .json",
      "chN": 55
    },
    {
      "index": 86,
      "pos": "Bae_TB_7_1186",
      "token_next_uri": " un.json",
      "token_prev_uri": "ng .json",
      "chN": 145
    },
    {
      "index": 419,
      "pos": "Bae_TB_7_1231",
      "token_next_uri": " un.json",
      "token_prev_uri": "ng .json",
      "chN": 733
    },
    {
      "index": 1,
      "pos_pr": "Bae_TB_7_1763",
      "pos_nxt": "Bae_TB_7_1765",
      "token_next_uri": " un.json",
      "token_prev_uri": "rg .json",
      "chN": 4
    },
    {
      "index": 40,
      "pos": "Bae_TB_7_2207",
      "token_next_uri": " un.json",
      "token_prev_uri": "ng .json",
      "chN": 120
    },
    {
      "index": 8,
      "pos": "Bae_TB_7_2520",
      "token_next_uri": " un.json",
      "token_prev_uri": "ig .json",
      "chN": 105
    },
    {
      "index": 0,
      "pos_pr": "Bae_TB_7_3243",
      "pos_nxt": "Bae_TB_7_3249",
      "token_next_uri": " un.json",
      "token_prev_uri": "ng .json",
      "chN": 4
    },
    {
      "index": 1,
      "pos_pr": "Bae_TB_7_3517",
      "pos_nxt": "Bae_TB_7_3523",
      "token_next_uri": " uU+002E.json",
      "token_prev_uri": "ng .json",
      "chN": 4
    },
    {
      "index": 0,
      "pos_pr": "Bae_TB_7_3879",
      "pos_nxt": "Bae_TB_7_3885",
      "token_next_uri": " un.json",
      "token_prev_uri": "ag .json",
      "chN": 4
    },
    {
      "index": 0,
      "pos_pr": "Bae_TB_7_4619",
      "pos_nxt": "Bae_TB_7_4625",
      "token_next_uri": " un.json",
      "token_prev_uri": "ig .json",
      "chN": 4
    },
    {
      "index": 0,
      "pos_pr": "Bae_TB_7_4815",
      "pos_nxt": "Bae_TB_7_4821",
      "token_next_uri": " un.json",
      "token_prev_uri": "ig .json",
      "chN": 4
    },
    {
      "index": 68,
      "pos": "Bae_TB_7_4971",
      "token_next_uri": " un.json",
      "token_prev_uri": "ng .json",
      "chN": 173
    },
    {
      "index": 38,
      "pos": "Bae_TB_7_4983",
      "token_next_uri": " un.json",
      "token_prev_uri": "ng .json",
      "chN": 170
    },
    {
      "index": 10,
      "pos": "Bae_TB_7_4985",
      "token_next_uri": " un.json",
      "token_prev_uri": "ng .json",
      "chN": 54
    },
    {
      "index": 0,
      "pos_pr": "Bae_TB_7_5658",
      "pos_nxt": "Bae_TB_7_5664",
      "token_next_uri": " un.json",
      "token_prev_uri": "ig .json",
      "chN": 4
    },
    {
      "index": 0,
      "pos_pr": "Bae_TB_7_9068",
      "pos_nxt": "Bae_TB_7_9074",
      "token_next_uri": " un.json",
      "token_prev_uri": "ng .json",
      "chN": 4
    },
    {
      "index": 9,
      "pos": "Bae_TB_7_9651",
      "token_next_uri": " un.json",
      "token_prev_uri": "ig .json",
      "chN": 31
    },
    {
      "index": 112,
      "pos": "Bae_TB_7_9934",
      "token_next_uri": " un.json",
      "token_prev_uri": "ng .json",
      "chN": 138
    },
    {
      "index": 0,
      "pos_pr": "Bae_TB_7_10113",
      "pos_nxt": "Bae_TB_7_10119",
      "token_next_uri": " un.json",
      "token_prev_uri": "ng .json",
      "chN": 4
    },
    {
      "index": 0,
      "pos_pr": "Bae_TB_7_10197",
      "pos_nxt": "Bae_TB_7_10203",
      "token_next_uri": " un.json",
      "token_prev_uri": "ng .json",
      "chN": 4
    },
    {
      "index": 0,
      "pos_pr": "Bae_TB_7_10206",
      "pos_nxt": "Bae_TB_7_10212",
      "token_next_uri": " un.json",
      "token_prev_uri": "ag .json",
      "chN": 4
    },
    {
      "index": 0,
      "pos_pr": "Bae_TB_7_12593",
      "pos_nxt": "Bae_TB_7_12599",
      "token_next_uri": " un.json",
      "token_prev_uri": "ng .json",
      "chN": 4
    },
    {
      "index": 0,
      "pos_pr": "Bae_TB_7_12765",
      "pos_nxt": "Bae_TB_7_12771",
      "token_next_uri": " un.json",
      "token_prev_uri": "ng .json",
      "chN": 4
    },
    {
      "index": 0,
      "pos_pr": "Bae_TB_7_13069",
      "pos_nxt": "Bae_TB_7_13075",
      "token_next_uri": " un.json",
      "token_prev_uri": "ig .json",
      "chN": 4
    },
    {
      "index": 386,
      "pos": "Bae_TB_7_13178",
      "token_next_uri": " un.json",
      "token_prev_uri": "ng .json",
      "chN": 1721
    },
    {
      "index": 25,
      "pos": "Bae_TB_7_13227",
      "token_next_uri": " un.json",
      "token_prev_uri": "ng .json",
      "chN": 168
    },
    {
      "index": 21,
      "pos": "Bae_TB_7_13265",
      "token_next_uri": " un.json",
      "token_prev_uri": "ng .json",
      "chN": 37
    },
    {
      "index": 151,
      "pos": "Bae_TB_7_13272",
      "token_next_uri": " un.json",
      "token_prev_uri": "ng .json",
      "chN": 260
    },
    {
      "index": 81,
      "pos": "Bae_TB_7_13329",
      "token_next_uri": " un.json",
      "token_prev_uri": "ng .json",
      "chN": 169
    },
    {
      "index": 146,
      "pos": "Bae_TB_7_13359",
      "token_next_uri": " un.json",
      "token_prev_uri": "ng .json",
      "chN": 879
    },
    {
      "index": 212,
      "pos": "Bae_TB_7_13386",
      "token_next_uri": " un.json",
      "token_prev_uri": "ng .json",
      "chN": 556
    },
    {
      "index": 60,
      "pos": "Bae_TB_7_13513",
      "token_next_uri": " un.json",
      "token_prev_uri": "ng .json",
      "chN": 423
    },
    {
      "index": 1241,
      "pos": "Bae_TB_7_13529",
      "token_next_uri": " um.json",
      "token_prev_uri": "ig .json",
      "chN": 1328
    },
    {
      "index": 15,
      "pos": "Bae_TB_8_359",
      "token_next_uri": " un.json",
      "token_prev_uri": "ng .json",
      "chN": 114
    },
    {
      "index": 30,
      "pos": "Bae_TB_8_359",
      "token_next_uri": " un.json",
      "token_prev_uri": "ng .json",
      "chN": 114
    },
    {
      "index": 27,
      "pos": "Bae_TB_8_800",
      "token_next_uri": " un.json",
      "token_prev_uri": "ng .json",
      "chN": 59
    },
    {
      "index": 0,
      "pos_pr": "Bae_TB_8_1776",
      "pos_nxt": "Bae_TB_8_1782",
      "token_next_uri": " un.json",
      "token_prev_uri": "ig .json",
      "chN": 4
    },
    {
      "index": 0,
      "pos_pr": "Bae_TB_8_2222",
      "pos_nxt": "Bae_TB_8_2228",
      "token_next_uri": " un.json",
      "token_prev_uri": "ng .json",
      "chN": 4
    },
    {
      "index": 54,
      "pos": "Bae_TB_8_2457",
      "token_next_uri": " un.json",
      "token_prev_uri": "ng .json",
      "chN": 117
    },
    {
      "index": 0,
      "pos_pr": "Bae_TB_8_4389",
      "pos_nxt": "Bae_TB_8_4395",
      "token_next_uri": " un.json",
      "token_prev_uri": "ng .json",
      "chN": 4
    },
    {
      "index": 0,
      "pos_pr": "Bae_TB_8_5014",
      "pos_nxt": "Bae_TB_8_5020",
      "token_next_uri": " un.json",
      "token_prev_uri": "ng .json",
      "chN": 4
    },
    {
      "index": 88,
      "pos": "Bae_TB_8_5213",
      "token_next_uri": " un.json",
      "token_prev_uri": "ng .json",
      "chN": 115
    },
    {
      "index": 294,
      "pos": "Bae_TB_8_5220",
      "token_next_uri": " un.json",
      "token_prev_uri": "ng .json",
      "chN": 304
    },
    {
      "index": 70,
      "pos": "Bae_TB_8_5339",
      "token_next_uri": " un.json",
      "token_prev_uri": "ng .json",
      "chN": 139
    },
    {
      "index": 0,
      "pos_pr": "Bae_TB_8_5870",
      "pos_nxt": "Bae_TB_8_5877",
      "token_next_uri": " un.json",
      "token_prev_uri": "ig .json",
      "chN": 4
    },
    {
      "index": 73,
      "pos": "Bae_TB_8_5884",
      "token_next_uri": " un.json",
      "token_prev_uri": "ig .json",
      "chN": 155
    }
  ]
}